Compiled from "FixedAreaSpawner.java"
public class com.cobblemon.mod.common.api.spawning.spawner.FixedAreaSpawner extends com.cobblemon.mod.common.api.spawning.spawner.BasicSpawner {
  private final net.minecraft.class_3218 world;

  private final net.minecraft.class_2338 position;

  private final int horizontalRadius;

  private final int verticalRadius;

  public com.cobblemon.mod.common.api.spawning.spawner.FixedAreaSpawner(java.lang.String, com.cobblemon.mod.common.api.spawning.detail.SpawnPool, net.minecraft.class_3218, net.minecraft.class_2338, int, int, float);
    Code:
       0: aload_1
       1: ldc           #50                 // String name
       3: invokestatic  #56                 // Method kotlin/jvm/internal/Intrinsics.checkNotNullParameter:(Ljava/lang/Object;Ljava/lang/String;)V
       6: aload_2
       7: ldc           #57                 // String spawnPool
       9: invokestatic  #56                 // Method kotlin/jvm/internal/Intrinsics.checkNotNullParameter:(Ljava/lang/Object;Ljava/lang/String;)V
      12: aload_3
      13: ldc           #58                 // String world
      15: invokestatic  #56                 // Method kotlin/jvm/internal/Intrinsics.checkNotNullParameter:(Ljava/lang/Object;Ljava/lang/String;)V
      18: aload         4
      20: ldc           #59                 // String position
      22: invokestatic  #56                 // Method kotlin/jvm/internal/Intrinsics.checkNotNullParameter:(Ljava/lang/Object;Ljava/lang/String;)V
      25: aload_0
      26: aload_1
      27: aload_2
      28: fload         7
      30: invokespecial #62                 // Method com/cobblemon/mod/common/api/spawning/spawner/BasicSpawner."<init>":(Ljava/lang/String;Lcom/cobblemon/mod/common/api/spawning/detail/SpawnPool;F)V
      33: aload_0
      34: aload_3
      35: putfield      #64                 // Field world:Lnet/minecraft/class_3218;
      38: aload_0
      39: aload         4
      41: putfield      #66                 // Field position:Lnet/minecraft/class_2338;
      44: aload_0
      45: iload         5
      47: putfield      #68                 // Field horizontalRadius:I
      50: aload_0
      51: iload         6
      53: putfield      #70                 // Field verticalRadius:I
      56: return

  public com.cobblemon.mod.common.api.spawning.spawner.FixedAreaSpawner(java.lang.String, com.cobblemon.mod.common.api.spawning.detail.SpawnPool, net.minecraft.class_3218, net.minecraft.class_2338, int, int, float, int, kotlin.jvm.internal.DefaultConstructorMarker);
    Code:
       0: iload         8
       2: bipush        64
       4: iand
       5: ifeq          19
       8: getstatic     #80                 // Field com/cobblemon/mod/common/Cobblemon.INSTANCE:Lcom/cobblemon/mod/common/Cobblemon;
      11: invokevirtual #84                 // Method com/cobblemon/mod/common/Cobblemon.getConfig:()Lcom/cobblemon/mod/common/config/CobblemonConfig;
      14: invokevirtual #90                 // Method com/cobblemon/mod/common/config/CobblemonConfig.getPokemonPerChunk:()F
      17: fstore        7
      19: aload_0
      20: aload_1
      21: aload_2
      22: aload_3
      23: aload         4
      25: iload         5
      27: iload         6
      29: fload         7
      31: invokespecial #92                 // Method "<init>":(Ljava/lang/String;Lcom/cobblemon/mod/common/api/spawning/detail/SpawnPool;Lnet/minecraft/class_3218;Lnet/minecraft/class_2338;IIF)V
      34: return

  public final net.minecraft.class_3218 getWorld();
    Code:
       0: aload_0
       1: getfield      #64                 // Field world:Lnet/minecraft/class_3218;
       4: areturn

  public final net.minecraft.class_2338 getPosition();
    Code:
       0: aload_0
       1: getfield      #66                 // Field position:Lnet/minecraft/class_2338;
       4: areturn

  public final int getHorizontalRadius();
    Code:
       0: aload_0
       1: getfield      #68                 // Field horizontalRadius:I
       4: ireturn

  public final int getVerticalRadius();
    Code:
       0: aload_0
       1: getfield      #70                 // Field verticalRadius:I
       4: ireturn

  public final java.util.List<java.lang.Object> run(com.cobblemon.mod.common.api.spawning.SpawnCause, java.lang.Integer);
    Code:
       0: aload_1
       1: ldc           #95                 // String cause
       3: invokestatic  #56                 // Method kotlin/jvm/internal/Intrinsics.checkNotNullParameter:(Ljava/lang/Object;Ljava/lang/String;)V
       6: aload_0
       7: aload_0
       8: aload_1
       9: invokevirtual #97                 // Method getZoneInput:(Lcom/cobblemon/mod/common/api/spawning/SpawnCause;)Lcom/cobblemon/mod/common/api/spawning/spawner/SpawningZoneInput;
      12: aload_2
      13: invokevirtual #101                // Method runForArea:(Lcom/cobblemon/mod/common/api/spawning/spawner/SpawningZoneInput;Ljava/lang/Integer;)Ljava/util/List;
      16: areturn

  public static java.util.List run$default(com.cobblemon.mod.common.api.spawning.spawner.FixedAreaSpawner, com.cobblemon.mod.common.api.spawning.SpawnCause, java.lang.Integer, int, java.lang.Object);
    Code:
       0: aload         4
       2: ifnull        15
       5: new           #106                // class java/lang/UnsupportedOperationException
       8: dup
       9: ldc           #108                // String Super calls with default arguments not supported in this target, function: run
      11: invokespecial #111                // Method java/lang/UnsupportedOperationException."<init>":(Ljava/lang/String;)V
      14: athrow
      15: iload_3
      16: iconst_2
      17: iand
      18: ifeq          23
      21: aconst_null
      22: astore_2
      23: aload_0
      24: aload_1
      25: aload_2
      26: invokevirtual #113                // Method run:(Lcom/cobblemon/mod/common/api/spawning/SpawnCause;Ljava/lang/Integer;)Ljava/util/List;
      29: areturn

  public final com.cobblemon.mod.common.api.spawning.spawner.SpawningZoneInput getZoneInput(com.cobblemon.mod.common.api.spawning.SpawnCause);
    Code:
       0: aload_1
       1: ldc           #95                 // String cause
       3: invokestatic  #56                 // Method kotlin/jvm/internal/Intrinsics.checkNotNullParameter:(Ljava/lang/Object;Ljava/lang/String;)V
       6: aload_0
       7: getfield      #66                 // Field position:Lnet/minecraft/class_2338;
      10: aload_0
      11: getfield      #68                 // Field horizontalRadius:I
      14: ineg
      15: aload_0
      16: getfield      #70                 // Field verticalRadius:I
      19: ineg
      20: aload_0
      21: getfield      #68                 // Field horizontalRadius:I
      24: ineg
      25: invokevirtual #119                // Method net/minecraft/class_2338.method_10069:(III)Lnet/minecraft/class_2338;
      28: astore_2
      29: new           #121                // class com/cobblemon/mod/common/api/spawning/spawner/SpawningZoneInput
      32: dup
      33: aload_1
      34: aload_0
      35: getfield      #64                 // Field world:Lnet/minecraft/class_3218;
      38: aload_2
      39: invokevirtual #124                // Method net/minecraft/class_2338.method_10263:()I
      42: aload_2
      43: invokevirtual #127                // Method net/minecraft/class_2338.method_10264:()I
      46: aload_2
      47: invokevirtual #130                // Method net/minecraft/class_2338.method_10260:()I
      50: aload_0
      51: getfield      #68                 // Field horizontalRadius:I
      54: iconst_2
      55: imul
      56: iconst_1
      57: iadd
      58: aload_0
      59: getfield      #70                 // Field verticalRadius:I
      62: iconst_2
      63: imul
      64: iconst_1
      65: iadd
      66: aload_0
      67: getfield      #68                 // Field horizontalRadius:I
      70: iconst_2
      71: imul
      72: iconst_1
      73: iadd
      74: invokespecial #133                // Method com/cobblemon/mod/common/api/spawning/spawner/SpawningZoneInput."<init>":(Lcom/cobblemon/mod/common/api/spawning/SpawnCause;Lnet/minecraft/class_3218;IIIIII)V
      77: areturn
}
