Compiled from "PokemonPastureBlockEntity.java"
public final class com.cobblemon.mod.common.block.entity.PokemonPastureBlockEntity extends net.minecraft.class_2586 {
  public static final com.cobblemon.mod.common.block.entity.PokemonPastureBlockEntity$Companion Companion;

  private int ticksUntilCheck;

  private final java.util.List<com.cobblemon.mod.common.block.entity.PokemonPastureBlockEntity$Tethering> tetheredPokemon;

  private net.minecraft.class_2338 minRoamPos;

  private net.minecraft.class_2338 maxRoamPos;

  private java.util.UUID ownerId;

  private java.lang.String ownerName;

  private static final net.minecraft.class_5558<com.cobblemon.mod.common.block.entity.PokemonPastureBlockEntity> TICKER;

  public com.cobblemon.mod.common.block.entity.PokemonPastureBlockEntity(net.minecraft.class_2338, net.minecraft.class_2680);
    Code:
       0: aload_1
       1: ldc           #135                // String pos
       3: invokestatic  #141                // Method kotlin/jvm/internal/Intrinsics.checkNotNullParameter:(Ljava/lang/Object;Ljava/lang/String;)V
       6: aload_2
       7: ldc           #142                // String state
       9: invokestatic  #141                // Method kotlin/jvm/internal/Intrinsics.checkNotNullParameter:(Ljava/lang/Object;Ljava/lang/String;)V
      12: aload_0
      13: getstatic     #148                // Field com/cobblemon/mod/common/CobblemonBlockEntities.PASTURE:Lnet/minecraft/class_2591;
      16: aload_1
      17: aload_2
      18: invokespecial #151                // Method net/minecraft/class_2586."<init>":(Lnet/minecraft/class_2591;Lnet/minecraft/class_2338;Lnet/minecraft/class_2680;)V
      21: aload_0
      22: getstatic     #157                // Field com/cobblemon/mod/common/Cobblemon.INSTANCE:Lcom/cobblemon/mod/common/Cobblemon;
      25: invokevirtual #161                // Method com/cobblemon/mod/common/Cobblemon.getConfig:()Lcom/cobblemon/mod/common/config/CobblemonConfig;
      28: invokevirtual #166                // Method com/cobblemon/mod/common/config/CobblemonConfig.getPastureBlockUpdateTicks:()I
      31: putfield      #168                // Field ticksUntilCheck:I
      34: aload_0
      35: new           #170                // class java/util/ArrayList
      38: dup
      39: invokespecial #172                // Method java/util/ArrayList."<init>":()V
      42: checkcast     #174                // class java/util/List
      45: putfield      #176                // Field tetheredPokemon:Ljava/util/List;
      48: aload_0
      49: ldc           #177                // String
      51: putfield      #179                // Field ownerName:Ljava/lang/String;
      54: nop
      55: getstatic     #157                // Field com/cobblemon/mod/common/Cobblemon.INSTANCE:Lcom/cobblemon/mod/common/Cobblemon;
      58: invokevirtual #161                // Method com/cobblemon/mod/common/Cobblemon.getConfig:()Lcom/cobblemon/mod/common/config/CobblemonConfig;
      61: invokevirtual #182                // Method com/cobblemon/mod/common/config/CobblemonConfig.getPastureMaxWanderDistance:()I
      64: istore_3
      65: aload_0
      66: aload_1
      67: new           #184                // class net/minecraft/class_2382
      70: dup
      71: iload_3
      72: iload_3
      73: iload_3
      74: invokespecial #187                // Method net/minecraft/class_2382."<init>":(III)V
      77: invokevirtual #193                // Method net/minecraft/class_2338.method_10059:(Lnet/minecraft/class_2382;)Lnet/minecraft/class_2338;
      80: dup
      81: ldc           #195                // String subtract(...)
      83: invokestatic  #198                // Method kotlin/jvm/internal/Intrinsics.checkNotNullExpressionValue:(Ljava/lang/Object;Ljava/lang/String;)V
      86: putfield      #200                // Field minRoamPos:Lnet/minecraft/class_2338;
      89: aload_0
      90: aload_1
      91: new           #184                // class net/minecraft/class_2382
      94: dup
      95: iload_3
      96: iload_3
      97: iload_3
      98: invokespecial #187                // Method net/minecraft/class_2382."<init>":(III)V
     101: invokevirtual #203                // Method net/minecraft/class_2338.method_10081:(Lnet/minecraft/class_2382;)Lnet/minecraft/class_2338;
     104: dup
     105: ldc           #205                // String offset(...)
     107: invokestatic  #198                // Method kotlin/jvm/internal/Intrinsics.checkNotNullExpressionValue:(Ljava/lang/Object;Ljava/lang/String;)V
     110: putfield      #207                // Field maxRoamPos:Lnet/minecraft/class_2338;
     113: nop
     114: return

  public final int getTicksUntilCheck();
    Code:
       0: aload_0
       1: getfield      #168                // Field ticksUntilCheck:I
       4: ireturn

  public final void setTicksUntilCheck(int);
    Code:
       0: aload_0
       1: iload_1
       2: putfield      #168                // Field ticksUntilCheck:I
       5: return

  public final java.util.List<com.cobblemon.mod.common.block.entity.PokemonPastureBlockEntity$Tethering> getTetheredPokemon();
    Code:
       0: aload_0
       1: getfield      #176                // Field tetheredPokemon:Ljava/util/List;
       4: areturn

  public final net.minecraft.class_2338 getMinRoamPos();
    Code:
       0: aload_0
       1: getfield      #200                // Field minRoamPos:Lnet/minecraft/class_2338;
       4: areturn

  public final void setMinRoamPos(net.minecraft.class_2338);
    Code:
       0: aload_1
       1: ldc           #212                // String <set-?>
       3: invokestatic  #141                // Method kotlin/jvm/internal/Intrinsics.checkNotNullParameter:(Ljava/lang/Object;Ljava/lang/String;)V
       6: aload_0
       7: aload_1
       8: putfield      #200                // Field minRoamPos:Lnet/minecraft/class_2338;
      11: return

  public final net.minecraft.class_2338 getMaxRoamPos();
    Code:
       0: aload_0
       1: getfield      #207                // Field maxRoamPos:Lnet/minecraft/class_2338;
       4: areturn

  public final void setMaxRoamPos(net.minecraft.class_2338);
    Code:
       0: aload_1
       1: ldc           #212                // String <set-?>
       3: invokestatic  #141                // Method kotlin/jvm/internal/Intrinsics.checkNotNullParameter:(Ljava/lang/Object;Ljava/lang/String;)V
       6: aload_0
       7: aload_1
       8: putfield      #207                // Field maxRoamPos:Lnet/minecraft/class_2338;
      11: return

  public final java.util.UUID getOwnerId();
    Code:
       0: aload_0
       1: getfield      #214                // Field ownerId:Ljava/util/UUID;
       4: areturn

  public final void setOwnerId(java.util.UUID);
    Code:
       0: aload_0
       1: aload_1
       2: putfield      #214                // Field ownerId:Ljava/util/UUID;
       5: return

  public final java.lang.String getOwnerName();
    Code:
       0: aload_0
       1: getfield      #179                // Field ownerName:Ljava/lang/String;
       4: areturn

  public final void setOwnerName(java.lang.String);
    Code:
       0: aload_1
       1: ldc           #212                // String <set-?>
       3: invokestatic  #141                // Method kotlin/jvm/internal/Intrinsics.checkNotNullParameter:(Ljava/lang/Object;Ljava/lang/String;)V
       6: aload_0
       7: aload_1
       8: putfield      #179                // Field ownerName:Ljava/lang/String;
      11: return

  public final int getMaxTethered();
    Code:
       0: getstatic     #157                // Field com/cobblemon/mod/common/Cobblemon.INSTANCE:Lcom/cobblemon/mod/common/Cobblemon;
       3: invokevirtual #161                // Method com/cobblemon/mod/common/Cobblemon.getConfig:()Lcom/cobblemon/mod/common/config/CobblemonConfig;
       6: invokevirtual #217                // Method com/cobblemon/mod/common/config/CobblemonConfig.getDefaultPasturedPokemonLimit:()I
       9: ireturn

  public final boolean canAddPokemon(net.minecraft.class_3222, com.cobblemon.mod.common.pokemon.Pokemon, int);
    Code:
       0: aload_1
       1: ldc           #218                // String player
       3: invokestatic  #141                // Method kotlin/jvm/internal/Intrinsics.checkNotNullParameter:(Ljava/lang/Object;Ljava/lang/String;)V
       6: aload_2
       7: ldc           #219                // String pokemon
       9: invokestatic  #141                // Method kotlin/jvm/internal/Intrinsics.checkNotNullParameter:(Ljava/lang/Object;Ljava/lang/String;)V
      12: aload_0
      13: getfield      #176                // Field tetheredPokemon:Ljava/util/List;
      16: checkcast     #221                // class java/lang/Iterable
      19: astore        5
      21: iconst_0
      22: istore        6
      24: aload         5
      26: instanceof    #223                // class java/util/Collection
      29: ifeq          49
      32: aload         5
      34: checkcast     #223                // class java/util/Collection
      37: invokeinterface #227,  1          // InterfaceMethod java/util/Collection.isEmpty:()Z
      42: ifeq          49
      45: iconst_0
      46: goto          121
      49: iconst_0
      50: istore        7
      52: aload         5
      54: invokeinterface #231,  1          // InterfaceMethod java/lang/Iterable.iterator:()Ljava/util/Iterator;
      59: astore        8
      61: aload         8
      63: invokeinterface #236,  1          // InterfaceMethod java/util/Iterator.hasNext:()Z
      68: ifeq          119
      71: aload         8
      73: invokeinterface #240,  1          // InterfaceMethod java/util/Iterator.next:()Ljava/lang/Object;
      78: astore        9
      80: aload         9
      82: checkcast     #115                // class com/cobblemon/mod/common/block/entity/PokemonPastureBlockEntity$Tethering
      85: astore        10
      87: iconst_0
      88: istore        11
      90: aload         10
      92: invokevirtual #243                // Method com/cobblemon/mod/common/block/entity/PokemonPastureBlockEntity$Tethering.getPlayerId:()Ljava/util/UUID;
      95: aload_1
      96: invokevirtual #248                // Method net/minecraft/class_3222.method_5667:()Ljava/util/UUID;
      99: invokestatic  #252                // Method kotlin/jvm/internal/Intrinsics.areEqual:(Ljava/lang/Object;Ljava/lang/Object;)Z
     102: ifeq          61
     105: iinc          7, 1
     108: iload         7
     110: ifge          61
     113: invokestatic  #257                // Method kotlin/collections/CollectionsKt.throwCountOverflow:()V
     116: goto          61
     119: iload         7
     121: istore        4
     123: iload         4
     125: iload_3
     126: if_icmpge     152
     129: aload_0
     130: getfield      #176                // Field tetheredPokemon:Ljava/util/List;
     133: invokeinterface #262,  1          // InterfaceMethod java/util/List.size:()I
     138: aload_0
     139: invokevirtual #264                // Method getMaxTethered:()I
     142: if_icmpge     152
     145: aload_2
     146: invokevirtual #267                // Method com/cobblemon/mod/common/pokemon/Pokemon.isFainted:()Z
     149: ifeq          154
     152: iconst_0
     153: ireturn
     154: getstatic     #157                // Field com/cobblemon/mod/common/Cobblemon.INSTANCE:Lcom/cobblemon/mod/common/Cobblemon;
     157: invokevirtual #161                // Method com/cobblemon/mod/common/Cobblemon.getConfig:()Lcom/cobblemon/mod/common/config/CobblemonConfig;
     160: invokevirtual #182                // Method com/cobblemon/mod/common/config/CobblemonConfig.getPastureMaxWanderDistance:()I
     163: i2d
     164: dstore        5
     166: aload_0
     167: invokevirtual #270                // Method method_11016:()Lnet/minecraft/class_2338;
     170: dup
     171: ldc_w         #272                // String getBlockPos(...)
     174: invokestatic  #198                // Method kotlin/jvm/internal/Intrinsics.checkNotNullExpressionValue:(Ljava/lang/Object;Ljava/lang/String;)V
     177: invokestatic  #278                // Method com/cobblemon/mod/common/util/BlockPosExtensionsKt.toVec3d:(Lnet/minecraft/class_2338;)Lnet/minecraft/class_243;
     180: dconst_1
     181: dconst_0
     182: dconst_1
     183: invokevirtual #284                // Method net/minecraft/class_243.method_18805:(DDD)Lnet/minecraft/class_243;
     186: astore        7
     188: aload_1
     189: invokevirtual #288                // Method net/minecraft/class_3222.method_37908:()Lnet/minecraft/class_1937;
     192: ldc_w         #290                // class com/cobblemon/mod/common/entity/pokemon/PokemonEntity
     195: aload         7
     197: dload         5
     199: ldc2_w        #291                // double 99999.0d
     202: dload         5
     204: invokestatic  #298                // Method net/minecraft/class_238.method_30048:(Lnet/minecraft/class_243;DDD)Lnet/minecraft/class_238;
     207: invokedynamic #318,  0            // InvokeDynamic #0:invoke:()Lkotlin/jvm/functions/Function1;
     212: invokedynamic #329,  0            // InvokeDynamic #1:test:(Lkotlin/jvm/functions/Function1;)Ljava/util/function/Predicate;
     217: invokevirtual #335                // Method net/minecraft/class_1937.method_8390:(Ljava/lang/Class;Lnet/minecraft/class_238;Ljava/util/function/Predicate;)Ljava/util/List;
     220: dup
     221: ldc_w         #337                // String getEntitiesOfClass(...)
     224: invokestatic  #198                // Method kotlin/jvm/internal/Intrinsics.checkNotNullExpressionValue:(Ljava/lang/Object;Ljava/lang/String;)V
     227: checkcast     #223                // class java/util/Collection
     230: invokeinterface #338,  1          // InterfaceMethod java/util/Collection.size:()I
     235: istore        8
     237: dload         5
     239: bipush        16
     241: i2d
     242: ddiv
     243: iconst_2
     244: i2d
     245: dmul
     246: dstore        9
     248: iload         8
     250: i2d
     251: getstatic     #157                // Field com/cobblemon/mod/common/Cobblemon.INSTANCE:Lcom/cobblemon/mod/common/Cobblemon;
     254: invokevirtual #161                // Method com/cobblemon/mod/common/Cobblemon.getConfig:()Lcom/cobblemon/mod/common/config/CobblemonConfig;
     257: invokevirtual #342                // Method com/cobblemon/mod/common/config/CobblemonConfig.getPastureMaxPerChunk:()F
     260: f2d
     261: dload         9
     263: dmul
     264: dload         9
     266: dmul
     267: dcmpl
     268: iflt          318
     271: getstatic     #347                // Field com/cobblemon/mod/common/CobblemonNetwork.INSTANCE:Lcom/cobblemon/mod/common/CobblemonNetwork;
     274: aload_1
     275: new           #349                // class com/cobblemon/mod/common/net/messages/client/pasture/ClosePasturePacket
     278: dup
     279: invokespecial #350                // Method com/cobblemon/mod/common/net/messages/client/pasture/ClosePasturePacket."<init>":()V
     282: checkcast     #352                // class com/cobblemon/mod/common/api/net/NetworkPacket
     285: invokevirtual #356                // Method com/cobblemon/mod/common/CobblemonNetwork.sendPacket:(Lnet/minecraft/class_3222;Lcom/cobblemon/mod/common/api/net/NetworkPacket;)V
     288: aload_1
     289: ldc_w         #358                // String pasture.too_many_nearby
     292: iconst_0
     293: anewarray     #360                // class java/lang/Object
     296: invokestatic  #366                // Method com/cobblemon/mod/common/util/LocalizationUtilsKt.lang:(Ljava/lang/String;[Ljava/lang/Object;)Lnet/minecraft/class_5250;
     299: dup
     300: ldc_w         #368                // String lang(...)
     303: invokestatic  #198                // Method kotlin/jvm/internal/Intrinsics.checkNotNullExpressionValue:(Ljava/lang/Object;Ljava/lang/String;)V
     306: invokestatic  #374                // Method com/cobblemon/mod/common/api/text/TextKt.red:(Lnet/minecraft/class_5250;)Lnet/minecraft/class_5250;
     309: checkcast     #376                // class net/minecraft/class_2561
     312: iconst_1
     313: invokevirtual #380                // Method net/minecraft/class_3222.method_43502:(Lnet/minecraft/class_2561;Z)V
     316: iconst_0
     317: ireturn
     318: iconst_1
     319: ireturn

  public final boolean tether(net.minecraft.class_3222, com.cobblemon.mod.common.pokemon.Pokemon, net.minecraft.class_2350);
    Code:
       0: aload_1
       1: ldc           #218                // String player
       3: invokestatic  #141                // Method kotlin/jvm/internal/Intrinsics.checkNotNullParameter:(Ljava/lang/Object;Ljava/lang/String;)V
       6: aload_2
       7: ldc           #219                // String pokemon
       9: invokestatic  #141                // Method kotlin/jvm/internal/Intrinsics.checkNotNullParameter:(Ljava/lang/Object;Ljava/lang/String;)V
      12: aload_3
      13: ldc_w         #395                // String directionToBehind
      16: invokestatic  #141                // Method kotlin/jvm/internal/Intrinsics.checkNotNullParameter:(Ljava/lang/Object;Ljava/lang/String;)V
      19: aload_0
      20: getfield      #398                // Field field_11863:Lnet/minecraft/class_1937;
      23: dup
      24: ifnonnull     30
      27: pop
      28: iconst_0
      29: ireturn
      30: astore        4
      32: new           #290                // class com/cobblemon/mod/common/entity/pokemon/PokemonEntity
      35: dup
      36: aload         4
      38: aload_2
      39: aconst_null
      40: iconst_4
      41: aconst_null
      42: invokespecial #401                // Method com/cobblemon/mod/common/entity/pokemon/PokemonEntity."<init>":(Lnet/minecraft/class_1937;Lcom/cobblemon/mod/common/pokemon/Pokemon;Lnet/minecraft/class_1299;ILkotlin/jvm/internal/DefaultConstructorMarker;)V
      45: astore        5
      47: aload         5
      49: invokevirtual #404                // Method com/cobblemon/mod/common/entity/pokemon/PokemonEntity.method_18382:()V
      52: aload         5
      54: invokevirtual #408                // Method com/cobblemon/mod/common/entity/pokemon/PokemonEntity.method_5829:()Lnet/minecraft/class_238;
      57: invokevirtual #412                // Method net/minecraft/class_238.method_17939:()D
      60: dstore        6
      62: aload_0
      63: invokevirtual #270                // Method method_11016:()Lnet/minecraft/class_2338;
      66: aload_3
      67: invokevirtual #418                // Method net/minecraft/class_2350.method_10163:()Lnet/minecraft/class_2382;
      70: dload         6
      72: invokestatic  #424                // Method java/lang/Math.ceil:(D)D
      75: d2i
      76: iconst_1
      77: iadd
      78: invokevirtual #428                // Method net/minecraft/class_2382.method_35862:(I)Lnet/minecraft/class_2382;
      81: invokevirtual #203                // Method net/minecraft/class_2338.method_10081:(Lnet/minecraft/class_2382;)Lnet/minecraft/class_2338;
      84: astore        8
      86: aload         5
      88: getstatic     #434                // Field net/minecraft/class_4050.field_18076:Lnet/minecraft/class_4050;
      91: invokevirtual #438                // Method com/cobblemon/mod/common/entity/pokemon/PokemonEntity.method_18377:(Lnet/minecraft/class_4050;)Lnet/minecraft/class_4048;
      94: aload         8
      96: invokevirtual #442                // Method net/minecraft/class_2338.method_46558:()Lnet/minecraft/class_243;
      99: dconst_0
     100: ldc2_w        #443                // double 0.5d
     103: dconst_0
     104: invokevirtual #447                // Method net/minecraft/class_243.method_1023:(DDD)Lnet/minecraft/class_243;
     107: invokevirtual #453                // Method net/minecraft/class_4048.method_30757:(Lnet/minecraft/class_243;)Lnet/minecraft/class_238;
     110: astore        9
     112: iconst_0
     113: istore        10
     115: iload         10
     117: bipush        6
     119: if_icmpge     442
     122: aload         9
     124: aload_3
     125: invokevirtual #418                // Method net/minecraft/class_2350.method_10163:()Lnet/minecraft/class_2382;
     128: invokevirtual #456                // Method net/minecraft/class_2382.method_10263:()I
     131: i2d
     132: dconst_0
     133: aload_3
     134: invokevirtual #418                // Method net/minecraft/class_2350.method_10163:()Lnet/minecraft/class_2382;
     137: invokevirtual #459                // Method net/minecraft/class_2382.method_10260:()I
     140: i2d
     141: invokevirtual #463                // Method net/minecraft/class_238.method_989:(DDD)Lnet/minecraft/class_238;
     144: astore        9
     146: aload_0
     147: aload         4
     149: aload         8
     151: aload_3
     152: invokevirtual #418                // Method net/minecraft/class_2350.method_10163:()Lnet/minecraft/class_2382;
     155: iload         10
     157: iconst_1
     158: iadd
     159: invokevirtual #428                // Method net/minecraft/class_2382.method_35862:(I)Lnet/minecraft/class_2382;
     162: invokevirtual #203                // Method net/minecraft/class_2338.method_10081:(Lnet/minecraft/class_2382;)Lnet/minecraft/class_2338;
     165: dup
     166: ldc           #205                // String offset(...)
     168: invokestatic  #198                // Method kotlin/jvm/internal/Intrinsics.checkNotNullExpressionValue:(Ljava/lang/Object;Ljava/lang/String;)V
     171: aload         5
     173: aload         9
     175: astore        12
     177: aload         12
     179: invokestatic  #467                // Method kotlin/jvm/internal/Intrinsics.checkNotNull:(Ljava/lang/Object;)V
     182: aload         12
     184: invokevirtual #469                // Method makeSuitableY:(Lnet/minecraft/class_1937;Lnet/minecraft/class_2338;Lcom/cobblemon/mod/common/entity/pokemon/PokemonEntity;Lnet/minecraft/class_238;)Lnet/minecraft/class_2338;
     187: astore        11
     189: aload         11
     191: ifnull        436
     194: aload         5
     196: aload         11
     198: invokevirtual #442                // Method net/minecraft/class_2338.method_46558:()Lnet/minecraft/class_243;
     201: dconst_0
     202: ldc2_w        #443                // double 0.5d
     205: dconst_0
     206: invokevirtual #447                // Method net/minecraft/class_243.method_1023:(DDD)Lnet/minecraft/class_243;
     209: invokevirtual #473                // Method com/cobblemon/mod/common/entity/pokemon/PokemonEntity.method_33574:(Lnet/minecraft/class_243;)V
     212: getstatic     #157                // Field com/cobblemon/mod/common/Cobblemon.INSTANCE:Lcom/cobblemon/mod/common/Cobblemon;
     215: invokevirtual #477                // Method com/cobblemon/mod/common/Cobblemon.getStorage:()Lcom/cobblemon/mod/common/api/storage/PokemonStoreManager;
     218: aload_1
     219: invokevirtual #483                // Method com/cobblemon/mod/common/api/storage/PokemonStoreManager.getPC:(Lnet/minecraft/class_3222;)Lcom/cobblemon/mod/common/api/storage/pc/PCStore;
     222: astore        12
     224: aload         5
     226: iconst_2
     227: invokevirtual #486                // Method com/cobblemon/mod/common/entity/pokemon/PokemonEntity.setBeamMode:(I)V
     230: ldc_w         #487                // float 0.5f
     233: aload         5
     235: invokedynamic #498,  0            // InvokeDynamic #2:invoke:(Lcom/cobblemon/mod/common/entity/pokemon/PokemonEntity;)Lkotlin/jvm/functions/Function0;
     240: invokestatic  #504                // Method com/cobblemon/mod/common/api/scheduling/SchedulingFunctionsKt.afterOnServer:(FLkotlin/jvm/functions/Function0;)Lcom/cobblemon/mod/common/api/scheduling/ScheduledTask;
     243: pop
     244: aload         4
     246: aload         5
     248: checkcast     #506                // class net/minecraft/class_1297
     251: invokevirtual #510                // Method net/minecraft/class_1937.method_8649:(Lnet/minecraft/class_1297;)Z
     254: ifeq          422
     257: new           #115                // class com/cobblemon/mod/common/block/entity/PokemonPastureBlockEntity$Tethering
     260: dup
     261: aload_0
     262: getfield      #200                // Field minRoamPos:Lnet/minecraft/class_2338;
     265: aload_0
     266: getfield      #207                // Field maxRoamPos:Lnet/minecraft/class_2338;
     269: aload_1
     270: invokevirtual #248                // Method net/minecraft/class_3222.method_5667:()Ljava/util/UUID;
     273: dup
     274: ldc_w         #512                // String getUUID(...)
     277: invokestatic  #198                // Method kotlin/jvm/internal/Intrinsics.checkNotNullExpressionValue:(Ljava/lang/Object;Ljava/lang/String;)V
     280: aload_1
     281: invokevirtual #516                // Method net/minecraft/class_3222.method_7334:()Lcom/mojang/authlib/GameProfile;
     284: invokevirtual #521                // Method com/mojang/authlib/GameProfile.getName:()Ljava/lang/String;
     287: dup
     288: ldc_w         #523                // String getName(...)
     291: invokestatic  #198                // Method kotlin/jvm/internal/Intrinsics.checkNotNullExpressionValue:(Ljava/lang/Object;Ljava/lang/String;)V
     294: invokestatic  #528                // Method java/util/UUID.randomUUID:()Ljava/util/UUID;
     297: dup
     298: ldc_w         #530                // String randomUUID(...)
     301: invokestatic  #198                // Method kotlin/jvm/internal/Intrinsics.checkNotNullExpressionValue:(Ljava/lang/Object;Ljava/lang/String;)V
     304: aload_2
     305: invokevirtual #533                // Method com/cobblemon/mod/common/pokemon/Pokemon.getUuid:()Ljava/util/UUID;
     308: dup
     309: ldc_w         #535                // String <get-uuid>(...)
     312: invokestatic  #198                // Method kotlin/jvm/internal/Intrinsics.checkNotNullExpressionValue:(Ljava/lang/Object;Ljava/lang/String;)V
     315: aload         12
     317: invokevirtual #538                // Method com/cobblemon/mod/common/api/storage/pc/PCStore.getUuid:()Ljava/util/UUID;
     320: aload         5
     322: invokevirtual #541                // Method com/cobblemon/mod/common/entity/pokemon/PokemonEntity.method_5628:()I
     325: aload_0
     326: invokevirtual #270                // Method method_11016:()Lnet/minecraft/class_2338;
     329: dup
     330: ldc_w         #272                // String getBlockPos(...)
     333: invokestatic  #198                // Method kotlin/jvm/internal/Intrinsics.checkNotNullExpressionValue:(Ljava/lang/Object;Ljava/lang/String;)V
     336: invokespecial #544                // Method com/cobblemon/mod/common/block/entity/PokemonPastureBlockEntity$Tethering."<init>":(Lnet/minecraft/class_2338;Lnet/minecraft/class_2338;Ljava/util/UUID;Ljava/lang/String;Ljava/util/UUID;Ljava/util/UUID;Ljava/util/UUID;ILnet/minecraft/class_2338;)V
     339: astore        13
     341: aload_2
     342: aload         13
     344: invokevirtual #547                // Method com/cobblemon/mod/common/block/entity/PokemonPastureBlockEntity$Tethering.getTetheringId:()Ljava/util/UUID;
     347: invokevirtual #550                // Method com/cobblemon/mod/common/pokemon/Pokemon.setTetheringId:(Ljava/util/UUID;)V
     350: aload_0
     351: getfield      #176                // Field tetheredPokemon:Ljava/util/List;
     354: aload         13
     356: invokeinterface #553,  2          // InterfaceMethod java/util/List.add:(Ljava/lang/Object;)Z
     361: pop
     362: aload         5
     364: aload         13
     366: invokevirtual #557                // Method com/cobblemon/mod/common/entity/pokemon/PokemonEntity.setTethering:(Lcom/cobblemon/mod/common/block/entity/PokemonPastureBlockEntity$Tethering;)V
     369: aload         13
     371: aload_1
     372: invokevirtual #561                // Method com/cobblemon/mod/common/block/entity/PokemonPastureBlockEntity$Tethering.toDTO:(Lnet/minecraft/class_3222;)Lcom/cobblemon/mod/common/net/messages/client/pasture/OpenPasturePacket$PasturePokemonDataDTO;
     375: dup
     376: ifnull        406
     379: astore        14
     381: iconst_0
     382: istore        15
     384: getstatic     #347                // Field com/cobblemon/mod/common/CobblemonNetwork.INSTANCE:Lcom/cobblemon/mod/common/CobblemonNetwork;
     387: aload_1
     388: new           #563                // class com/cobblemon/mod/common/net/messages/client/pasture/PokemonPasturedPacket
     391: dup
     392: aload         14
     394: invokespecial #566                // Method com/cobblemon/mod/common/net/messages/client/pasture/PokemonPasturedPacket."<init>":(Lcom/cobblemon/mod/common/net/messages/client/pasture/OpenPasturePacket$PasturePokemonDataDTO;)V
     397: checkcast     #352                // class com/cobblemon/mod/common/api/net/NetworkPacket
     400: invokevirtual #356                // Method com/cobblemon/mod/common/CobblemonNetwork.sendPacket:(Lnet/minecraft/class_3222;Lcom/cobblemon/mod/common/api/net/NetworkPacket;)V
     403: goto          408
     406: pop
     407: nop
     408: aload_0
     409: invokevirtual #569                // Method method_5431:()V
     412: getstatic     #575                // Field com/cobblemon/mod/common/advancement/CobblemonCriteria.PASTURE_USE:Lcom/cobblemon/mod/common/advancement/criterion/SimpleCriterionTrigger;
     415: aload_1
     416: aload_2
     417: invokevirtual #581                // Method com/cobblemon/mod/common/advancement/criterion/SimpleCriterionTrigger.trigger:(Lnet/minecraft/class_3222;Ljava/lang/Object;)V
     420: iconst_1
     421: ireturn
     422: getstatic     #585                // Field com/cobblemon/mod/common/Cobblemon.LOGGER:Lorg/apache/logging/log4j/Logger;
     425: ldc_w         #587                // String Couldn\'t spawn pastured Pokémon for some reason
     428: invokeinterface #592,  2          // InterfaceMethod org/apache/logging/log4j/Logger.warn:(Ljava/lang/String;)V
     433: goto          442
     436: iinc          10, 1
     439: goto          115
     442: iconst_0
     443: ireturn

  private final void togglePastureOn(boolean);
    Code:
       0: aload_0
       1: invokevirtual #607                // Method method_11010:()Lnet/minecraft/class_2680;
       4: invokevirtual #613                // Method net/minecraft/class_2680.method_26204:()Lnet/minecraft/class_2248;
       7: dup
       8: ldc_w         #615                // String null cannot be cast to non-null type com.cobblemon.mod.common.block.PastureBlock
      11: invokestatic  #617                // Method kotlin/jvm/internal/Intrinsics.checkNotNull:(Ljava/lang/Object;Ljava/lang/String;)V
      14: checkcast     #111                // class com/cobblemon/mod/common/block/PastureBlock
      17: astore_2
      18: aload_0
      19: getfield      #398                // Field field_11863:Lnet/minecraft/class_1937;
      22: astore_3
      23: aload_3
      24: ifnull        334
      27: aload_3
      28: getfield      #621                // Field net/minecraft/class_1937.field_9236:Z
      31: ifne          334
      34: aload_3
      35: astore        4
      37: aload_2
      38: aload_0
      39: invokevirtual #607                // Method method_11010:()Lnet/minecraft/class_2680;
      42: dup
      43: ldc_w         #623                // String getBlockState(...)
      46: invokestatic  #198                // Method kotlin/jvm/internal/Intrinsics.checkNotNullExpressionValue:(Ljava/lang/Object;Ljava/lang/String;)V
      49: aload_0
      50: invokevirtual #270                // Method method_11016:()Lnet/minecraft/class_2338;
      53: dup
      54: ldc_w         #272                // String getBlockPos(...)
      57: invokestatic  #198                // Method kotlin/jvm/internal/Intrinsics.checkNotNullExpressionValue:(Ljava/lang/Object;Ljava/lang/String;)V
      60: invokevirtual #627                // Method com/cobblemon/mod/common/block/PastureBlock.getBasePosition:(Lnet/minecraft/class_2680;Lnet/minecraft/class_2338;)Lnet/minecraft/class_2338;
      63: astore        5
      65: aload         4
      67: aload         5
      69: invokevirtual #631                // Method net/minecraft/class_1937.method_8320:(Lnet/minecraft/class_2338;)Lnet/minecraft/class_2680;
      72: astore        6
      74: aload_2
      75: aload         6
      77: invokestatic  #467                // Method kotlin/jvm/internal/Intrinsics.checkNotNull:(Ljava/lang/Object;)V
      80: aload         6
      82: aload         5
      84: invokevirtual #634                // Method com/cobblemon/mod/common/block/PastureBlock.getPositionOfOtherPart:(Lnet/minecraft/class_2680;Lnet/minecraft/class_2338;)Lnet/minecraft/class_2338;
      87: astore        7
      89: aload         4
      91: aload         7
      93: invokevirtual #631                // Method net/minecraft/class_1937.method_8320:(Lnet/minecraft/class_2338;)Lnet/minecraft/class_2680;
      96: astore        8
      98: nop
      99: aload         6
     101: getstatic     #637                // Field com/cobblemon/mod/common/block/PastureBlock.Companion:Lcom/cobblemon/mod/common/block/PastureBlock$Companion;
     104: invokevirtual #641                // Method com/cobblemon/mod/common/block/PastureBlock$Companion.getON:()Lnet/minecraft/class_2746;
     107: checkcast     #643                // class net/minecraft/class_2769
     110: invokevirtual #647                // Method net/minecraft/class_2680.method_11654:(Lnet/minecraft/class_2769;)Ljava/lang/Comparable;
     113: iload_1
     114: invokestatic  #653                // Method java/lang/Boolean.valueOf:(Z)Ljava/lang/Boolean;
     117: invokestatic  #252                // Method kotlin/jvm/internal/Intrinsics.areEqual:(Ljava/lang/Object;Ljava/lang/Object;)Z
     120: ifne          334
     123: aload         4
     125: aload         7
     127: aload         8
     129: getstatic     #637                // Field com/cobblemon/mod/common/block/PastureBlock.Companion:Lcom/cobblemon/mod/common/block/PastureBlock$Companion;
     132: invokevirtual #641                // Method com/cobblemon/mod/common/block/PastureBlock$Companion.getON:()Lnet/minecraft/class_2746;
     135: checkcast     #643                // class net/minecraft/class_2769
     138: iload_1
     139: invokestatic  #653                // Method java/lang/Boolean.valueOf:(Z)Ljava/lang/Boolean;
     142: checkcast     #655                // class java/lang/Comparable
     145: invokevirtual #659                // Method net/minecraft/class_2680.method_11657:(Lnet/minecraft/class_2769;Ljava/lang/Comparable;)Ljava/lang/Object;
     148: checkcast     #609                // class net/minecraft/class_2680
     151: invokevirtual #663                // Method net/minecraft/class_1937.method_8501:(Lnet/minecraft/class_2338;Lnet/minecraft/class_2680;)Z
     154: pop
     155: aload         4
     157: aload         5
     159: aload         6
     161: getstatic     #637                // Field com/cobblemon/mod/common/block/PastureBlock.Companion:Lcom/cobblemon/mod/common/block/PastureBlock$Companion;
     164: invokevirtual #641                // Method com/cobblemon/mod/common/block/PastureBlock$Companion.getON:()Lnet/minecraft/class_2746;
     167: checkcast     #643                // class net/minecraft/class_2769
     170: iload_1
     171: invokestatic  #653                // Method java/lang/Boolean.valueOf:(Z)Ljava/lang/Boolean;
     174: checkcast     #655                // class java/lang/Comparable
     177: invokevirtual #659                // Method net/minecraft/class_2680.method_11657:(Lnet/minecraft/class_2769;Ljava/lang/Comparable;)Ljava/lang/Object;
     180: checkcast     #609                // class net/minecraft/class_2680
     183: invokevirtual #663                // Method net/minecraft/class_1937.method_8501:(Lnet/minecraft/class_2338;Lnet/minecraft/class_2680;)Z
     186: pop
     187: goto          334
     190: astore        9
     192: aload         4
     194: aload_0
     195: invokevirtual #270                // Method method_11016:()Lnet/minecraft/class_2338;
     198: invokevirtual #666                // Method net/minecraft/class_2338.method_10084:()Lnet/minecraft/class_2338;
     201: invokevirtual #631                // Method net/minecraft/class_1937.method_8320:(Lnet/minecraft/class_2338;)Lnet/minecraft/class_2680;
     204: invokevirtual #613                // Method net/minecraft/class_2680.method_26204:()Lnet/minecraft/class_2248;
     207: instanceof    #111                // class com/cobblemon/mod/common/block/PastureBlock
     210: ifeq          234
     213: aload         4
     215: aload_0
     216: invokevirtual #270                // Method method_11016:()Lnet/minecraft/class_2338;
     219: invokevirtual #666                // Method net/minecraft/class_2338.method_10084:()Lnet/minecraft/class_2338;
     222: getstatic     #672                // Field net/minecraft/class_2246.field_10124:Lnet/minecraft/class_2248;
     225: invokevirtual #677                // Method net/minecraft/class_2248.method_9564:()Lnet/minecraft/class_2680;
     228: invokevirtual #663                // Method net/minecraft/class_1937.method_8501:(Lnet/minecraft/class_2338;Lnet/minecraft/class_2680;)Z
     231: goto          252
     234: aload         4
     236: aload_0
     237: invokevirtual #270                // Method method_11016:()Lnet/minecraft/class_2338;
     240: invokevirtual #680                // Method net/minecraft/class_2338.method_10074:()Lnet/minecraft/class_2338;
     243: getstatic     #672                // Field net/minecraft/class_2246.field_10124:Lnet/minecraft/class_2248;
     246: invokevirtual #677                // Method net/minecraft/class_2248.method_9564:()Lnet/minecraft/class_2680;
     249: invokevirtual #663                // Method net/minecraft/class_1937.method_8501:(Lnet/minecraft/class_2338;Lnet/minecraft/class_2680;)Z
     252: pop
     253: aload         4
     255: aload_0
     256: invokevirtual #270                // Method method_11016:()Lnet/minecraft/class_2338;
     259: getstatic     #672                // Field net/minecraft/class_2246.field_10124:Lnet/minecraft/class_2248;
     262: invokevirtual #677                // Method net/minecraft/class_2248.method_9564:()Lnet/minecraft/class_2680;
     265: invokevirtual #663                // Method net/minecraft/class_1937.method_8501:(Lnet/minecraft/class_2338;Lnet/minecraft/class_2680;)Z
     268: pop
     269: aload         4
     271: new           #682                // class net/minecraft/class_1542
     274: dup
     275: aload         4
     277: aload_0
     278: invokevirtual #270                // Method method_11016:()Lnet/minecraft/class_2338;
     281: invokevirtual #683                // Method net/minecraft/class_2338.method_10263:()I
     284: i2d
     285: ldc2_w        #443                // double 0.5d
     288: dadd
     289: aload_0
     290: invokevirtual #270                // Method method_11016:()Lnet/minecraft/class_2338;
     293: invokevirtual #686                // Method net/minecraft/class_2338.method_10264:()I
     296: i2d
     297: dconst_1
     298: dadd
     299: aload_0
     300: invokevirtual #270                // Method method_11016:()Lnet/minecraft/class_2338;
     303: invokevirtual #687                // Method net/minecraft/class_2338.method_10260:()I
     306: i2d
     307: ldc2_w        #443                // double 0.5d
     310: dadd
     311: new           #689                // class net/minecraft/class_1799
     314: dup
     315: getstatic     #694                // Field com/cobblemon/mod/common/CobblemonBlocks.PASTURE:Lcom/cobblemon/mod/common/block/PastureBlock;
     318: checkcast     #696                // class net/minecraft/class_1935
     321: invokespecial #699                // Method net/minecraft/class_1799."<init>":(Lnet/minecraft/class_1935;)V
     324: invokespecial #702                // Method net/minecraft/class_1542."<init>":(Lnet/minecraft/class_1937;DDDLnet/minecraft/class_1799;)V
     327: checkcast     #506                // class net/minecraft/class_1297
     330: invokevirtual #510                // Method net/minecraft/class_1937.method_8649:(Lnet/minecraft/class_1297;)Z
     333: pop
     334: return
    Exception table:
       from    to  target type
          98   187   190   Class java/lang/IllegalArgumentException

  public final boolean isSafeFloor(net.minecraft.class_1937, net.minecraft.class_2338, com.cobblemon.mod.common.entity.pokemon.PokemonEntity);
    Code:
       0: aload_1
       1: ldc_w         #711                // String world
       4: invokestatic  #141                // Method kotlin/jvm/internal/Intrinsics.checkNotNullParameter:(Ljava/lang/Object;Ljava/lang/String;)V
       7: aload_2
       8: ldc           #135                // String pos
      10: invokestatic  #141                // Method kotlin/jvm/internal/Intrinsics.checkNotNullParameter:(Ljava/lang/Object;Ljava/lang/String;)V
      13: aload_3
      14: ldc_w         #712                // String entity
      17: invokestatic  #141                // Method kotlin/jvm/internal/Intrinsics.checkNotNullParameter:(Ljava/lang/Object;Ljava/lang/String;)V
      20: aload_1
      21: aload_2
      22: invokevirtual #631                // Method net/minecraft/class_1937.method_8320:(Lnet/minecraft/class_2338;)Lnet/minecraft/class_2680;
      25: astore        4
      27: aload         4
      29: invokevirtual #715                // Method net/minecraft/class_2680.method_26215:()Z
      32: ifeq          39
      35: iconst_0
      36: goto          181
      39: aload         4
      41: aload_1
      42: checkcast     #717                // class net/minecraft/class_1922
      45: aload_2
      46: aload_3
      47: checkcast     #506                // class net/minecraft/class_1297
      50: invokevirtual #721                // Method net/minecraft/class_2680.method_26168:(Lnet/minecraft/class_1922;Lnet/minecraft/class_2338;Lnet/minecraft/class_1297;)Z
      53: ifne          76
      56: aload         4
      58: aload_1
      59: checkcast     #717                // class net/minecraft/class_1922
      62: aload_2
      63: aload_3
      64: checkcast     #506                // class net/minecraft/class_1297
      67: getstatic     #724                // Field net/minecraft/class_2350.field_11033:Lnet/minecraft/class_2350;
      70: invokevirtual #728                // Method net/minecraft/class_2680.method_26169:(Lnet/minecraft/class_1922;Lnet/minecraft/class_2338;Lnet/minecraft/class_1297;Lnet/minecraft/class_2350;)Z
      73: ifeq          80
      76: iconst_1
      77: goto          181
      80: aload_3
      81: invokevirtual #732                // Method com/cobblemon/mod/common/entity/pokemon/PokemonEntity.getBehaviour:()Lcom/cobblemon/mod/common/pokemon/ai/FormPokemonBehaviour;
      84: invokevirtual #738                // Method com/cobblemon/mod/common/pokemon/ai/FormPokemonBehaviour.getMoving:()Lcom/cobblemon/mod/common/pokemon/ai/MoveBehaviour;
      87: invokevirtual #744                // Method com/cobblemon/mod/common/pokemon/ai/MoveBehaviour.getSwim:()Lcom/cobblemon/mod/common/pokemon/ai/SwimBehaviour;
      90: invokevirtual #749                // Method com/cobblemon/mod/common/pokemon/ai/SwimBehaviour.getCanWalkOnWater:()Z
      93: ifne          112
      96: aload_3
      97: invokevirtual #732                // Method com/cobblemon/mod/common/entity/pokemon/PokemonEntity.getBehaviour:()Lcom/cobblemon/mod/common/pokemon/ai/FormPokemonBehaviour;
     100: invokevirtual #738                // Method com/cobblemon/mod/common/pokemon/ai/FormPokemonBehaviour.getMoving:()Lcom/cobblemon/mod/common/pokemon/ai/MoveBehaviour;
     103: invokevirtual #744                // Method com/cobblemon/mod/common/pokemon/ai/MoveBehaviour.getSwim:()Lcom/cobblemon/mod/common/pokemon/ai/SwimBehaviour;
     106: invokevirtual #752                // Method com/cobblemon/mod/common/pokemon/ai/SwimBehaviour.getCanSwimInWater:()Z
     109: ifeq          130
     112: aload         4
     114: invokevirtual #756                // Method net/minecraft/class_2680.method_26227:()Lnet/minecraft/class_3610;
     117: getstatic     #762                // Field net/minecraft/class_3486.field_15517:Lnet/minecraft/class_6862;
     120: invokevirtual #768                // Method net/minecraft/class_3610.method_15767:(Lnet/minecraft/class_6862;)Z
     123: ifeq          130
     126: iconst_1
     127: goto          181
     130: aload_3
     131: invokevirtual #732                // Method com/cobblemon/mod/common/entity/pokemon/PokemonEntity.getBehaviour:()Lcom/cobblemon/mod/common/pokemon/ai/FormPokemonBehaviour;
     134: invokevirtual #738                // Method com/cobblemon/mod/common/pokemon/ai/FormPokemonBehaviour.getMoving:()Lcom/cobblemon/mod/common/pokemon/ai/MoveBehaviour;
     137: invokevirtual #744                // Method com/cobblemon/mod/common/pokemon/ai/MoveBehaviour.getSwim:()Lcom/cobblemon/mod/common/pokemon/ai/SwimBehaviour;
     140: invokevirtual #771                // Method com/cobblemon/mod/common/pokemon/ai/SwimBehaviour.getCanWalkOnLava:()Z
     143: ifne          162
     146: aload_3
     147: invokevirtual #732                // Method com/cobblemon/mod/common/entity/pokemon/PokemonEntity.getBehaviour:()Lcom/cobblemon/mod/common/pokemon/ai/FormPokemonBehaviour;
     150: invokevirtual #738                // Method com/cobblemon/mod/common/pokemon/ai/FormPokemonBehaviour.getMoving:()Lcom/cobblemon/mod/common/pokemon/ai/MoveBehaviour;
     153: invokevirtual #744                // Method com/cobblemon/mod/common/pokemon/ai/MoveBehaviour.getSwim:()Lcom/cobblemon/mod/common/pokemon/ai/SwimBehaviour;
     156: invokevirtual #774                // Method com/cobblemon/mod/common/pokemon/ai/SwimBehaviour.getCanSwimInLava:()Z
     159: ifeq          180
     162: aload         4
     164: invokevirtual #756                // Method net/minecraft/class_2680.method_26227:()Lnet/minecraft/class_3610;
     167: getstatic     #777                // Field net/minecraft/class_3486.field_15518:Lnet/minecraft/class_6862;
     170: invokevirtual #768                // Method net/minecraft/class_3610.method_15767:(Lnet/minecraft/class_6862;)Z
     173: ifeq          180
     176: iconst_1
     177: goto          181
     180: iconst_0
     181: ireturn

  public final net.minecraft.class_2338 makeSuitableY(net.minecraft.class_1937, net.minecraft.class_2338, com.cobblemon.mod.common.entity.pokemon.PokemonEntity, net.minecraft.class_238);
    Code:
       0: aload_1
       1: ldc_w         #711                // String world
       4: invokestatic  #141                // Method kotlin/jvm/internal/Intrinsics.checkNotNullParameter:(Ljava/lang/Object;Ljava/lang/String;)V
       7: aload_2
       8: ldc           #135                // String pos
      10: invokestatic  #141                // Method kotlin/jvm/internal/Intrinsics.checkNotNullParameter:(Ljava/lang/Object;Ljava/lang/String;)V
      13: aload_3
      14: ldc_w         #712                // String entity
      17: invokestatic  #141                // Method kotlin/jvm/internal/Intrinsics.checkNotNullParameter:(Ljava/lang/Object;Ljava/lang/String;)V
      20: aload         4
      22: ldc_w         #778                // String box
      25: invokestatic  #141                // Method kotlin/jvm/internal/Intrinsics.checkNotNullParameter:(Ljava/lang/Object;Ljava/lang/String;)V
      28: aload_1
      29: aload_3
      30: checkcast     #506                // class net/minecraft/class_1297
      33: aload         4
      35: invokevirtual #782                // Method net/minecraft/class_1937.method_39454:(Lnet/minecraft/class_1297;Lnet/minecraft/class_238;)Z
      38: ifeq          120
      41: iconst_1
      42: istore        5
      44: iload         5
      46: bipush        16
      48: if_icmpge     202
      51: aload         4
      53: ldc2_w        #443                // double 0.5d
      56: iload         5
      58: i2d
      59: ldc2_w        #443                // double 0.5d
      62: invokevirtual #463                // Method net/minecraft/class_238.method_989:(DDD)Lnet/minecraft/class_238;
      65: astore        6
      67: aload_1
      68: aload_3
      69: checkcast     #506                // class net/minecraft/class_1297
      72: aload         6
      74: invokevirtual #782                // Method net/minecraft/class_1937.method_39454:(Lnet/minecraft/class_1297;Lnet/minecraft/class_238;)Z
      77: ifne          114
      80: aload_0
      81: aload_1
      82: aload_2
      83: iconst_0
      84: iload         5
      86: iconst_1
      87: isub
      88: iconst_0
      89: invokevirtual #786                // Method net/minecraft/class_2338.method_10069:(III)Lnet/minecraft/class_2338;
      92: dup
      93: ldc           #205                // String offset(...)
      95: invokestatic  #198                // Method kotlin/jvm/internal/Intrinsics.checkNotNullExpressionValue:(Ljava/lang/Object;Ljava/lang/String;)V
      98: aload_3
      99: invokevirtual #788                // Method isSafeFloor:(Lnet/minecraft/class_1937;Lnet/minecraft/class_2338;Lcom/cobblemon/mod/common/entity/pokemon/PokemonEntity;)Z
     102: ifeq          114
     105: aload_2
     106: iconst_0
     107: iload         5
     109: iconst_0
     110: invokevirtual #786                // Method net/minecraft/class_2338.method_10069:(III)Lnet/minecraft/class_2338;
     113: areturn
     114: iinc          5, 1
     117: goto          44
     120: iconst_1
     121: istore        5
     123: iload         5
     125: bipush        16
     127: if_icmpge     202
     130: aload         4
     132: ldc2_w        #443                // double 0.5d
     135: iload         5
     137: i2d
     138: dneg
     139: ldc2_w        #443                // double 0.5d
     142: invokevirtual #463                // Method net/minecraft/class_238.method_989:(DDD)Lnet/minecraft/class_238;
     145: astore        6
     147: aload_1
     148: aload_3
     149: checkcast     #506                // class net/minecraft/class_1297
     152: aload         6
     154: invokevirtual #782                // Method net/minecraft/class_1937.method_39454:(Lnet/minecraft/class_1297;Lnet/minecraft/class_238;)Z
     157: ifeq          196
     160: aload_0
     161: aload_1
     162: aload_2
     163: iconst_0
     164: iload         5
     166: ineg
     167: iconst_0
     168: invokevirtual #786                // Method net/minecraft/class_2338.method_10069:(III)Lnet/minecraft/class_2338;
     171: dup
     172: ldc           #205                // String offset(...)
     174: invokestatic  #198                // Method kotlin/jvm/internal/Intrinsics.checkNotNullExpressionValue:(Ljava/lang/Object;Ljava/lang/String;)V
     177: aload_3
     178: invokevirtual #788                // Method isSafeFloor:(Lnet/minecraft/class_1937;Lnet/minecraft/class_2338;Lcom/cobblemon/mod/common/entity/pokemon/PokemonEntity;)Z
     181: ifeq          196
     184: aload_2
     185: iconst_0
     186: iload         5
     188: ineg
     189: iconst_1
     190: iadd
     191: iconst_0
     192: invokevirtual #786                // Method net/minecraft/class_2338.method_10069:(III)Lnet/minecraft/class_2338;
     195: areturn
     196: iinc          5, 1
     199: goto          123
     202: aconst_null
     203: areturn

  public final void checkPokemon();
    Code:
       0: new           #170                // class java/util/ArrayList
       3: dup
       4: invokespecial #172                // Method java/util/ArrayList."<init>":()V
       7: checkcast     #174                // class java/util/List
      10: astore_1
      11: aload_0
      12: getfield      #176                // Field tetheredPokemon:Ljava/util/List;
      15: checkcast     #221                // class java/lang/Iterable
      18: astore_2
      19: iconst_0
      20: istore_3
      21: aload_2
      22: invokeinterface #231,  1          // InterfaceMethod java/lang/Iterable.iterator:()Ljava/util/Iterator;
      27: astore        4
      29: aload         4
      31: invokeinterface #236,  1          // InterfaceMethod java/util/Iterator.hasNext:()Z
      36: ifeq          126
      39: aload         4
      41: invokeinterface #240,  1          // InterfaceMethod java/util/Iterator.next:()Ljava/lang/Object;
      46: astore        5
      48: aload         5
      50: checkcast     #115                // class com/cobblemon/mod/common/block/entity/PokemonPastureBlockEntity$Tethering
      53: astore        6
      55: iconst_0
      56: istore        7
      58: aload         6
      60: invokevirtual #793                // Method com/cobblemon/mod/common/block/entity/PokemonPastureBlockEntity$Tethering.getPokemon:()Lcom/cobblemon/mod/common/pokemon/Pokemon;
      63: astore        8
      65: aload         8
      67: ifnonnull     85
      70: aload_1
      71: aload         6
      73: invokevirtual #796                // Method com/cobblemon/mod/common/block/entity/PokemonPastureBlockEntity$Tethering.getPokemonId:()Ljava/util/UUID;
      76: invokeinterface #553,  2          // InterfaceMethod java/util/List.add:(Ljava/lang/Object;)Z
      81: pop
      82: goto          121
      85: aload         8
      87: invokevirtual #797                // Method com/cobblemon/mod/common/pokemon/Pokemon.getTetheringId:()Ljava/util/UUID;
      90: ifnull        109
      93: aload         8
      95: invokevirtual #797                // Method com/cobblemon/mod/common/pokemon/Pokemon.getTetheringId:()Ljava/util/UUID;
      98: aload         6
     100: invokevirtual #547                // Method com/cobblemon/mod/common/block/entity/PokemonPastureBlockEntity$Tethering.getTetheringId:()Ljava/util/UUID;
     103: invokestatic  #252                // Method kotlin/jvm/internal/Intrinsics.areEqual:(Ljava/lang/Object;Ljava/lang/Object;)Z
     106: ifne          121
     109: aload_1
     110: aload         6
     112: invokevirtual #796                // Method com/cobblemon/mod/common/block/entity/PokemonPastureBlockEntity$Tethering.getPokemonId:()Ljava/util/UUID;
     115: invokeinterface #553,  2          // InterfaceMethod java/util/List.add:(Ljava/lang/Object;)Z
     120: pop
     121: nop
     122: nop
     123: goto          29
     126: nop
     127: aload_1
     128: checkcast     #221                // class java/lang/Iterable
     131: astore_2
     132: iconst_0
     133: istore_3
     134: aload_2
     135: invokeinterface #231,  1          // InterfaceMethod java/lang/Iterable.iterator:()Ljava/util/Iterator;
     140: astore        4
     142: aload         4
     144: invokeinterface #236,  1          // InterfaceMethod java/util/Iterator.hasNext:()Z
     149: ifeq          181
     152: aload         4
     154: invokeinterface #240,  1          // InterfaceMethod java/util/Iterator.next:()Ljava/lang/Object;
     159: astore        5
     161: aload         5
     163: checkcast     #525                // class java/util/UUID
     166: astore        6
     168: iconst_0
     169: istore        7
     171: aload_0
     172: aload         6
     174: invokevirtual #799                // Method releasePokemon:(Ljava/util/UUID;)V
     177: nop
     178: goto          142
     181: nop
     182: aload_0
     183: getstatic     #157                // Field com/cobblemon/mod/common/Cobblemon.INSTANCE:Lcom/cobblemon/mod/common/Cobblemon;
     186: invokevirtual #161                // Method com/cobblemon/mod/common/Cobblemon.getConfig:()Lcom/cobblemon/mod/common/config/CobblemonConfig;
     189: invokevirtual #166                // Method com/cobblemon/mod/common/config/CobblemonConfig.getPastureBlockUpdateTicks:()I
     192: putfield      #168                // Field ticksUntilCheck:I
     195: aload_0
     196: invokevirtual #569                // Method method_5431:()V
     199: return

  public final void onBroken();
    Code:
       0: aload_0
       1: getfield      #398                // Field field_11863:Lnet/minecraft/class_1937;
       4: instanceof    #807                // class net/minecraft/class_3218
       7: ifeq          102
      10: aload_0
      11: getfield      #176                // Field tetheredPokemon:Ljava/util/List;
      14: checkcast     #221                // class java/lang/Iterable
      17: invokestatic  #811                // Method kotlin/collections/CollectionsKt.toList:(Ljava/lang/Iterable;)Ljava/util/List;
      20: checkcast     #221                // class java/lang/Iterable
      23: astore_1
      24: iconst_0
      25: istore_2
      26: aload_1
      27: invokeinterface #231,  1          // InterfaceMethod java/lang/Iterable.iterator:()Ljava/util/Iterator;
      32: astore_3
      33: aload_3
      34: invokeinterface #236,  1          // InterfaceMethod java/util/Iterator.hasNext:()Z
      39: ifeq          73
      42: aload_3
      43: invokeinterface #240,  1          // InterfaceMethod java/util/Iterator.next:()Ljava/lang/Object;
      48: astore        4
      50: aload         4
      52: checkcast     #115                // class com/cobblemon/mod/common/block/entity/PokemonPastureBlockEntity$Tethering
      55: astore        5
      57: iconst_0
      58: istore        6
      60: aload_0
      61: aload         5
      63: invokevirtual #796                // Method com/cobblemon/mod/common/block/entity/PokemonPastureBlockEntity$Tethering.getPokemonId:()Ljava/util/UUID;
      66: invokevirtual #799                // Method releasePokemon:(Ljava/util/UUID;)V
      69: nop
      70: goto          33
      73: nop
      74: aload_0
      75: getfield      #398                // Field field_11863:Lnet/minecraft/class_1937;
      78: dup
      79: ldc_w         #813                // String null cannot be cast to non-null type net.minecraft.server.level.ServerLevel
      82: invokestatic  #617                // Method kotlin/jvm/internal/Intrinsics.checkNotNull:(Ljava/lang/Object;Ljava/lang/String;)V
      85: checkcast     #807                // class net/minecraft/class_3218
      88: aload_0
      89: invokevirtual #270                // Method method_11016:()Lnet/minecraft/class_2338;
      92: dup
      93: ldc_w         #272                // String getBlockPos(...)
      96: invokestatic  #198                // Method kotlin/jvm/internal/Intrinsics.checkNotNullExpressionValue:(Ljava/lang/Object;Ljava/lang/String;)V
      99: invokestatic  #819                // Method com/cobblemon/mod/common/api/pasture/PastureLinkManager.removeAt:(Lnet/minecraft/class_3218;Lnet/minecraft/class_2338;)V
     102: return

  public final void releasePokemon(java.util.UUID);
    Code:
       0: aload_1
       1: ldc_w         #821                // String pokemonId
       4: invokestatic  #141                // Method kotlin/jvm/internal/Intrinsics.checkNotNullParameter:(Ljava/lang/Object;Ljava/lang/String;)V
       7: aload_0
       8: getfield      #176                // Field tetheredPokemon:Ljava/util/List;
      11: checkcast     #221                // class java/lang/Iterable
      14: astore_3
      15: aload_3
      16: invokeinterface #231,  1          // InterfaceMethod java/lang/Iterable.iterator:()Ljava/util/Iterator;
      21: astore        4
      23: aload         4
      25: invokeinterface #236,  1          // InterfaceMethod java/util/Iterator.hasNext:()Z
      30: ifeq          69
      33: aload         4
      35: invokeinterface #240,  1          // InterfaceMethod java/util/Iterator.next:()Ljava/lang/Object;
      40: astore        5
      42: aload         5
      44: checkcast     #115                // class com/cobblemon/mod/common/block/entity/PokemonPastureBlockEntity$Tethering
      47: astore        6
      49: iconst_0
      50: istore        7
      52: aload         6
      54: invokevirtual #796                // Method com/cobblemon/mod/common/block/entity/PokemonPastureBlockEntity$Tethering.getPokemonId:()Ljava/util/UUID;
      57: aload_1
      58: invokestatic  #252                // Method kotlin/jvm/internal/Intrinsics.areEqual:(Ljava/lang/Object;Ljava/lang/Object;)Z
      61: ifeq          23
      64: aload         5
      66: goto          70
      69: aconst_null
      70: checkcast     #115                // class com/cobblemon/mod/common/block/entity/PokemonPastureBlockEntity$Tethering
      73: dup
      74: ifnonnull     79
      77: pop
      78: return
      79: astore_2
      80: aload_2
      81: invokevirtual #793                // Method com/cobblemon/mod/common/block/entity/PokemonPastureBlockEntity$Tethering.getPokemon:()Lcom/cobblemon/mod/common/pokemon/Pokemon;
      84: dup
      85: ifnull        95
      88: aconst_null
      89: invokevirtual #550                // Method com/cobblemon/mod/common/pokemon/Pokemon.setTetheringId:(Ljava/util/UUID;)V
      92: goto          96
      95: pop
      96: aload_0
      97: getfield      #176                // Field tetheredPokemon:Ljava/util/List;
     100: aload_2
     101: invokeinterface #824,  2          // InterfaceMethod java/util/List.remove:(Ljava/lang/Object;)Z
     106: pop
     107: aload_0
     108: invokevirtual #569                // Method method_5431:()V
     111: return

  public final java.util.List<java.util.UUID> releaseAllPokemon(java.util.UUID);
    Code:
       0: aload_1
       1: ldc_w         #827                // String playerId
       4: invokestatic  #141                // Method kotlin/jvm/internal/Intrinsics.checkNotNullParameter:(Ljava/lang/Object;Ljava/lang/String;)V
       7: new           #170                // class java/util/ArrayList
      10: dup
      11: invokespecial #172                // Method java/util/ArrayList."<init>":()V
      14: checkcast     #174                // class java/util/List
      17: astore_2
      18: aload_0
      19: getfield      #176                // Field tetheredPokemon:Ljava/util/List;
      22: checkcast     #221                // class java/lang/Iterable
      25: astore_3
      26: iconst_0
      27: istore        4
      29: aload_3
      30: astore        5
      32: new           #170                // class java/util/ArrayList
      35: dup
      36: invokespecial #172                // Method java/util/ArrayList."<init>":()V
      39: checkcast     #223                // class java/util/Collection
      42: astore        6
      44: iconst_0
      45: istore        7
      47: aload         5
      49: invokeinterface #231,  1          // InterfaceMethod java/lang/Iterable.iterator:()Ljava/util/Iterator;
      54: astore        8
      56: aload         8
      58: invokeinterface #236,  1          // InterfaceMethod java/util/Iterator.hasNext:()Z
      63: ifeq          110
      66: aload         8
      68: invokeinterface #240,  1          // InterfaceMethod java/util/Iterator.next:()Ljava/lang/Object;
      73: astore        9
      75: aload         9
      77: checkcast     #115                // class com/cobblemon/mod/common/block/entity/PokemonPastureBlockEntity$Tethering
      80: astore        10
      82: iconst_0
      83: istore        11
      85: aload         10
      87: invokevirtual #243                // Method com/cobblemon/mod/common/block/entity/PokemonPastureBlockEntity$Tethering.getPlayerId:()Ljava/util/UUID;
      90: aload_1
      91: invokestatic  #252                // Method kotlin/jvm/internal/Intrinsics.areEqual:(Ljava/lang/Object;Ljava/lang/Object;)Z
      94: ifeq          56
      97: aload         6
      99: aload         9
     101: invokeinterface #828,  2          // InterfaceMethod java/util/Collection.add:(Ljava/lang/Object;)Z
     106: pop
     107: goto          56
     110: aload         6
     112: checkcast     #174                // class java/util/List
     115: nop
     116: checkcast     #221                // class java/lang/Iterable
     119: astore_3
     120: nop
     121: iconst_0
     122: istore        4
     124: aload_3
     125: invokeinterface #231,  1          // InterfaceMethod java/lang/Iterable.iterator:()Ljava/util/Iterator;
     130: astore        5
     132: aload         5
     134: invokeinterface #236,  1          // InterfaceMethod java/util/Iterator.hasNext:()Z
     139: ifeq          207
     142: aload         5
     144: invokeinterface #240,  1          // InterfaceMethod java/util/Iterator.next:()Ljava/lang/Object;
     149: astore        6
     151: aload         6
     153: checkcast     #115                // class com/cobblemon/mod/common/block/entity/PokemonPastureBlockEntity$Tethering
     156: astore        7
     158: iconst_0
     159: istore        8
     161: aload         7
     163: invokevirtual #793                // Method com/cobblemon/mod/common/block/entity/PokemonPastureBlockEntity$Tethering.getPokemon:()Lcom/cobblemon/mod/common/pokemon/Pokemon;
     166: dup
     167: ifnull        177
     170: aconst_null
     171: invokevirtual #550                // Method com/cobblemon/mod/common/pokemon/Pokemon.setTetheringId:(Ljava/util/UUID;)V
     174: goto          178
     177: pop
     178: aload_0
     179: getfield      #176                // Field tetheredPokemon:Ljava/util/List;
     182: aload         7
     184: invokeinterface #824,  2          // InterfaceMethod java/util/List.remove:(Ljava/lang/Object;)Z
     189: pop
     190: aload_2
     191: aload         7
     193: invokevirtual #796                // Method com/cobblemon/mod/common/block/entity/PokemonPastureBlockEntity$Tethering.getPokemonId:()Ljava/util/UUID;
     196: invokeinterface #553,  2          // InterfaceMethod java/util/List.add:(Ljava/lang/Object;)Z
     201: pop
     202: nop
     203: nop
     204: goto          132
     207: nop
     208: aload_0
     209: invokevirtual #569                // Method method_5431:()V
     212: aload_2
     213: areturn

  private final int getInRangeViewerCount(net.minecraft.class_1937, net.minecraft.class_2338, double);
    Code:
       0: new           #294                // class net/minecraft/class_238
       3: dup
       4: aload_2
       5: invokevirtual #683                // Method net/minecraft/class_2338.method_10263:()I
       8: i2d
       9: dload_3
      10: dsub
      11: aload_2
      12: invokevirtual #686                // Method net/minecraft/class_2338.method_10264:()I
      15: i2d
      16: dload_3
      17: dsub
      18: aload_2
      19: invokevirtual #687                // Method net/minecraft/class_2338.method_10260:()I
      22: i2d
      23: dload_3
      24: dsub
      25: aload_2
      26: invokevirtual #683                // Method net/minecraft/class_2338.method_10263:()I
      29: iconst_1
      30: iadd
      31: i2d
      32: dload_3
      33: dadd
      34: aload_2
      35: invokevirtual #686                // Method net/minecraft/class_2338.method_10264:()I
      38: iconst_1
      39: iadd
      40: i2d
      41: dload_3
      42: dadd
      43: aload_2
      44: invokevirtual #687                // Method net/minecraft/class_2338.method_10260:()I
      47: iconst_1
      48: iadd
      49: i2d
      50: dload_3
      51: dadd
      52: invokespecial #841                // Method net/minecraft/class_238."<init>":(DDDDDD)V
      55: astore        5
      57: aload_1
      58: ldc           #245                // class net/minecraft/class_3222
      60: invokestatic  #847                // InterfaceMethod net/minecraft/class_5575.method_31795:(Ljava/lang/Class;)Lnet/minecraft/class_5575;
      63: aload         5
      65: new           #117                // class com/cobblemon/mod/common/block/entity/PokemonPastureBlockEntity$getInRangeViewerCount$1
      68: dup
      69: aload_0
      70: invokespecial #849                // Method com/cobblemon/mod/common/block/entity/PokemonPastureBlockEntity$getInRangeViewerCount$1."<init>":(Ljava/lang/Object;)V
      73: checkcast     #851                // class kotlin/jvm/functions/Function1
      76: invokedynamic #856,  0            // InvokeDynamic #3:test:(Lkotlin/jvm/functions/Function1;)Ljava/util/function/Predicate;
      81: invokevirtual #860                // Method net/minecraft/class_1937.method_18023:(Lnet/minecraft/class_5575;Lnet/minecraft/class_238;Ljava/util/function/Predicate;)Ljava/util/List;
      84: invokeinterface #262,  1          // InterfaceMethod java/util/List.size:()I
      89: ireturn

  static int getInRangeViewerCount$default(com.cobblemon.mod.common.block.entity.PokemonPastureBlockEntity, net.minecraft.class_1937, net.minecraft.class_2338, double, int, java.lang.Object);
    Code:
       0: iload         5
       2: iconst_4
       3: iand
       4: ifeq          11
       7: ldc2_w        #863                // double 5.0d
      10: dstore_3
      11: aload_0
      12: aload_1
      13: aload_2
      14: dload_3
      15: invokespecial #866                // Method getInRangeViewerCount:(Lnet/minecraft/class_1937;Lnet/minecraft/class_2338;D)I
      18: ireturn

  private final boolean isPlayerViewing(net.minecraft.class_3222);
    Code:
       0: aload_1
       1: invokestatic  #870                // Method com/cobblemon/mod/common/api/pasture/PastureLinkManager.getLinkByPlayer:(Lnet/minecraft/class_3222;)Lcom/cobblemon/mod/common/api/pasture/PastureLink;
       4: astore_2
       5: aload_2
       6: ifnull        52
       9: aload_2
      10: invokevirtual #875                // Method com/cobblemon/mod/common/api/pasture/PastureLink.getPos:()Lnet/minecraft/class_2338;
      13: aload_0
      14: invokevirtual #270                // Method method_11016:()Lnet/minecraft/class_2338;
      17: invokestatic  #252                // Method kotlin/jvm/internal/Intrinsics.areEqual:(Ljava/lang/Object;Ljava/lang/Object;)Z
      20: ifeq          52
      23: aload_2
      24: invokevirtual #879                // Method com/cobblemon/mod/common/api/pasture/PastureLink.getDimension:()Lnet/minecraft/class_2960;
      27: aload_1
      28: invokevirtual #288                // Method net/minecraft/class_3222.method_37908:()Lnet/minecraft/class_1937;
      31: invokevirtual #883                // Method net/minecraft/class_1937.method_40134:()Lnet/minecraft/class_6880;
      34: invokeinterface #888,  1          // InterfaceMethod net/minecraft/class_6880.method_55840:()Ljava/lang/String;
      39: invokestatic  #894                // Method net/minecraft/class_2960.method_12829:(Ljava/lang/String;)Lnet/minecraft/class_2960;
      42: invokestatic  #252                // Method kotlin/jvm/internal/Intrinsics.areEqual:(Ljava/lang/Object;Ljava/lang/Object;)Z
      45: ifeq          52
      48: iconst_1
      49: goto          53
      52: iconst_0
      53: ireturn

  protected void method_11014(net.minecraft.class_2487, net.minecraft.class_7225$class_7874);
    Code:
       0: aload_1
       1: ldc_w         #898                // String nbt
       4: invokestatic  #141                // Method kotlin/jvm/internal/Intrinsics.checkNotNullParameter:(Ljava/lang/Object;Ljava/lang/String;)V
       7: aload_2
       8: ldc_w         #899                // String registryLookup
      11: invokestatic  #141                // Method kotlin/jvm/internal/Intrinsics.checkNotNullParameter:(Ljava/lang/Object;Ljava/lang/String;)V
      14: aload_0
      15: aload_1
      16: aload_2
      17: invokespecial #901                // Method net/minecraft/class_2586.method_11014:(Lnet/minecraft/class_2487;Lnet/minecraft/class_7225$class_7874;)V
      20: aload_1
      21: ldc_w         #903                // String TetherPokemon
      24: bipush        10
      26: invokevirtual #909                // Method net/minecraft/class_2487.method_10554:(Ljava/lang/String;I)Lnet/minecraft/class_2499;
      29: astore_3
      30: aload_0
      31: aload_1
      32: ldc_w         #911                // String TetherOwnerId
      35: invokevirtual #915                // Method net/minecraft/class_2487.method_25928:(Ljava/lang/String;)Z
      38: ifeq          51
      41: aload_1
      42: ldc_w         #911                // String TetherOwnerId
      45: invokevirtual #919                // Method net/minecraft/class_2487.method_25926:(Ljava/lang/String;)Ljava/util/UUID;
      48: goto          52
      51: aconst_null
      52: putfield      #214                // Field ownerId:Ljava/util/UUID;
      55: aload_0
      56: aload_1
      57: ldc_w         #923                // String TetherOwnerName
      60: invokevirtual #927                // Method net/minecraft/class_2487.method_10558:(Ljava/lang/String;)Ljava/lang/String;
      63: astore        5
      65: aload         5
      67: astore        6
      69: astore        11
      71: iconst_0
      72: istore        7
      74: aload         6
      76: invokestatic  #467                // Method kotlin/jvm/internal/Intrinsics.checkNotNull:(Ljava/lang/Object;)V
      79: aload         6
      81: checkcast     #929                // class java/lang/CharSequence
      84: invokeinterface #932,  1          // InterfaceMethod java/lang/CharSequence.length:()I
      89: ifle          96
      92: iconst_1
      93: goto          97
      96: iconst_0
      97: nop
      98: istore        12
     100: aload         11
     102: iload         12
     104: ifeq          112
     107: aload         5
     109: goto          113
     112: aconst_null
     113: dup
     114: ifnonnull     120
     117: pop
     118: ldc           #177                // String
     120: putfield      #179                // Field ownerName:Ljava/lang/String;
     123: aload_3
     124: invokevirtual #935                // Method net/minecraft/class_2499.iterator:()Ljava/util/Iterator;
     127: dup
     128: ldc_w         #937                // String iterator(...)
     131: invokestatic  #198                // Method kotlin/jvm/internal/Intrinsics.checkNotNullExpressionValue:(Ljava/lang/Object;Ljava/lang/String;)V
     134: astore        4
     136: aload         4
     138: invokeinterface #236,  1          // InterfaceMethod java/util/Iterator.hasNext:()Z
     143: ifeq          310
     146: aload         4
     148: invokeinterface #240,  1          // InterfaceMethod java/util/Iterator.next:()Ljava/lang/Object;
     153: checkcast     #939                // class net/minecraft/class_2520
     156: astore        5
     158: aload         5
     160: ldc_w         #941                // String null cannot be cast to non-null type net.minecraft.nbt.CompoundTag
     163: invokestatic  #617                // Method kotlin/jvm/internal/Intrinsics.checkNotNull:(Ljava/lang/Object;Ljava/lang/String;)V
     166: aload         5
     168: checkcast     #905                // class net/minecraft/class_2487
     171: pop
     172: aload         5
     174: checkcast     #905                // class net/minecraft/class_2487
     177: ldc_w         #943                // String TetheringId
     180: invokevirtual #919                // Method net/minecraft/class_2487.method_25926:(Ljava/lang/String;)Ljava/util/UUID;
     183: astore        6
     185: aload         5
     187: checkcast     #905                // class net/minecraft/class_2487
     190: ldc_w         #945                // String UUID
     193: invokevirtual #919                // Method net/minecraft/class_2487.method_25926:(Ljava/lang/String;)Ljava/util/UUID;
     196: astore        7
     198: aload         5
     200: checkcast     #905                // class net/minecraft/class_2487
     203: ldc_w         #947                // String PCId
     206: invokevirtual #919                // Method net/minecraft/class_2487.method_25926:(Ljava/lang/String;)Ljava/util/UUID;
     209: astore        8
     211: aload         5
     213: checkcast     #905                // class net/minecraft/class_2487
     216: ldc_w         #949                // String PlayerId
     219: invokevirtual #919                // Method net/minecraft/class_2487.method_25926:(Ljava/lang/String;)Ljava/util/UUID;
     222: astore        9
     224: aload         5
     226: checkcast     #905                // class net/minecraft/class_2487
     229: ldc_w         #951                // String EntityId
     232: invokevirtual #955                // Method net/minecraft/class_2487.method_10550:(Ljava/lang/String;)I
     235: istore        10
     237: aload_0
     238: getfield      #176                // Field tetheredPokemon:Ljava/util/List;
     241: new           #115                // class com/cobblemon/mod/common/block/entity/PokemonPastureBlockEntity$Tethering
     244: dup
     245: aload_0
     246: getfield      #200                // Field minRoamPos:Lnet/minecraft/class_2338;
     249: aload_0
     250: getfield      #207                // Field maxRoamPos:Lnet/minecraft/class_2338;
     253: aload         9
     255: invokestatic  #467                // Method kotlin/jvm/internal/Intrinsics.checkNotNull:(Ljava/lang/Object;)V
     258: aload         9
     260: aload_0
     261: getfield      #179                // Field ownerName:Ljava/lang/String;
     264: aload         6
     266: invokestatic  #467                // Method kotlin/jvm/internal/Intrinsics.checkNotNull:(Ljava/lang/Object;)V
     269: aload         6
     271: aload         7
     273: invokestatic  #467                // Method kotlin/jvm/internal/Intrinsics.checkNotNull:(Ljava/lang/Object;)V
     276: aload         7
     278: aload         8
     280: invokestatic  #467                // Method kotlin/jvm/internal/Intrinsics.checkNotNull:(Ljava/lang/Object;)V
     283: aload         8
     285: iload         10
     287: aload_0
     288: invokevirtual #270                // Method method_11016:()Lnet/minecraft/class_2338;
     291: dup
     292: ldc_w         #272                // String getBlockPos(...)
     295: invokestatic  #198                // Method kotlin/jvm/internal/Intrinsics.checkNotNullExpressionValue:(Ljava/lang/Object;Ljava/lang/String;)V
     298: invokespecial #544                // Method com/cobblemon/mod/common/block/entity/PokemonPastureBlockEntity$Tethering."<init>":(Lnet/minecraft/class_2338;Lnet/minecraft/class_2338;Ljava/util/UUID;Ljava/lang/String;Ljava/util/UUID;Ljava/util/UUID;Ljava/util/UUID;ILnet/minecraft/class_2338;)V
     301: invokeinterface #553,  2          // InterfaceMethod java/util/List.add:(Ljava/lang/Object;)Z
     306: pop
     307: goto          136
     310: aload_0
     311: aload_1
     312: ldc_w         #957                // String TetherMinRoamPos
     315: invokestatic  #963                // Method net/minecraft/class_2512.method_10691:(Lnet/minecraft/class_2487;Ljava/lang/String;)Ljava/util/Optional;
     318: invokevirtual #968                // Method java/util/Optional.get:()Ljava/lang/Object;
     321: dup
     322: ldc_w         #970                // String get(...)
     325: invokestatic  #198                // Method kotlin/jvm/internal/Intrinsics.checkNotNullExpressionValue:(Ljava/lang/Object;Ljava/lang/String;)V
     328: checkcast     #189                // class net/minecraft/class_2338
     331: putfield      #200                // Field minRoamPos:Lnet/minecraft/class_2338;
     334: aload_0
     335: aload_1
     336: ldc_w         #972                // String TetherMaxRoamPos
     339: invokestatic  #963                // Method net/minecraft/class_2512.method_10691:(Lnet/minecraft/class_2487;Ljava/lang/String;)Ljava/util/Optional;
     342: invokevirtual #968                // Method java/util/Optional.get:()Ljava/lang/Object;
     345: dup
     346: ldc_w         #970                // String get(...)
     349: invokestatic  #198                // Method kotlin/jvm/internal/Intrinsics.checkNotNullExpressionValue:(Ljava/lang/Object;Ljava/lang/String;)V
     352: checkcast     #189                // class net/minecraft/class_2338
     355: putfield      #207                // Field maxRoamPos:Lnet/minecraft/class_2338;
     358: return

  protected void method_11007(net.minecraft.class_2487, net.minecraft.class_7225$class_7874);
    Code:
       0: aload_1
       1: ldc_w         #898                // String nbt
       4: invokestatic  #141                // Method kotlin/jvm/internal/Intrinsics.checkNotNullParameter:(Ljava/lang/Object;Ljava/lang/String;)V
       7: aload_2
       8: ldc_w         #899                // String registryLookup
      11: invokestatic  #141                // Method kotlin/jvm/internal/Intrinsics.checkNotNullParameter:(Ljava/lang/Object;Ljava/lang/String;)V
      14: aload_0
      15: aload_1
      16: aload_2
      17: invokespecial #983                // Method net/minecraft/class_2586.method_11007:(Lnet/minecraft/class_2487;Lnet/minecraft/class_7225$class_7874;)V
      20: new           #921                // class net/minecraft/class_2499
      23: dup
      24: invokespecial #984                // Method net/minecraft/class_2499."<init>":()V
      27: astore_3
      28: aload_0
      29: getfield      #176                // Field tetheredPokemon:Ljava/util/List;
      32: invokeinterface #985,  1          // InterfaceMethod java/util/List.iterator:()Ljava/util/Iterator;
      37: astore        4
      39: aload         4
      41: invokeinterface #236,  1          // InterfaceMethod java/util/Iterator.hasNext:()Z
      46: ifeq          145
      49: aload         4
      51: invokeinterface #240,  1          // InterfaceMethod java/util/Iterator.next:()Ljava/lang/Object;
      56: checkcast     #115                // class com/cobblemon/mod/common/block/entity/PokemonPastureBlockEntity$Tethering
      59: astore        5
      61: new           #905                // class net/minecraft/class_2487
      64: dup
      65: invokespecial #986                // Method net/minecraft/class_2487."<init>":()V
      68: astore        6
      70: aload         6
      72: ldc_w         #943                // String TetheringId
      75: aload         5
      77: invokevirtual #547                // Method com/cobblemon/mod/common/block/entity/PokemonPastureBlockEntity$Tethering.getTetheringId:()Ljava/util/UUID;
      80: invokevirtual #990                // Method net/minecraft/class_2487.method_25927:(Ljava/lang/String;Ljava/util/UUID;)V
      83: aload         6
      85: ldc_w         #949                // String PlayerId
      88: aload         5
      90: invokevirtual #243                // Method com/cobblemon/mod/common/block/entity/PokemonPastureBlockEntity$Tethering.getPlayerId:()Ljava/util/UUID;
      93: invokevirtual #990                // Method net/minecraft/class_2487.method_25927:(Ljava/lang/String;Ljava/util/UUID;)V
      96: aload         6
      98: ldc_w         #945                // String UUID
     101: aload         5
     103: invokevirtual #796                // Method com/cobblemon/mod/common/block/entity/PokemonPastureBlockEntity$Tethering.getPokemonId:()Ljava/util/UUID;
     106: invokevirtual #990                // Method net/minecraft/class_2487.method_25927:(Ljava/lang/String;Ljava/util/UUID;)V
     109: aload         6
     111: ldc_w         #947                // String PCId
     114: aload         5
     116: invokevirtual #993                // Method com/cobblemon/mod/common/block/entity/PokemonPastureBlockEntity$Tethering.getPcId:()Ljava/util/UUID;
     119: invokevirtual #990                // Method net/minecraft/class_2487.method_25927:(Ljava/lang/String;Ljava/util/UUID;)V
     122: aload         6
     124: ldc_w         #951                // String EntityId
     127: aload         5
     129: invokevirtual #996                // Method com/cobblemon/mod/common/block/entity/PokemonPastureBlockEntity$Tethering.getEntityId:()I
     132: invokevirtual #1000               // Method net/minecraft/class_2487.method_10569:(Ljava/lang/String;I)V
     135: aload_3
     136: aload         6
     138: invokevirtual #1001               // Method net/minecraft/class_2499.add:(Ljava/lang/Object;)Z
     141: pop
     142: goto          39
     145: aload_1
     146: ldc_w         #903                // String TetherPokemon
     149: aload_3
     150: checkcast     #939                // class net/minecraft/class_2520
     153: invokevirtual #1005               // Method net/minecraft/class_2487.method_10566:(Ljava/lang/String;Lnet/minecraft/class_2520;)Lnet/minecraft/class_2520;
     156: pop
     157: aload_1
     158: ldc_w         #957                // String TetherMinRoamPos
     161: aload_0
     162: getfield      #200                // Field minRoamPos:Lnet/minecraft/class_2338;
     165: invokestatic  #1009               // Method net/minecraft/class_2512.method_10692:(Lnet/minecraft/class_2338;)Lnet/minecraft/class_2520;
     168: invokevirtual #1005               // Method net/minecraft/class_2487.method_10566:(Ljava/lang/String;Lnet/minecraft/class_2520;)Lnet/minecraft/class_2520;
     171: pop
     172: aload_1
     173: ldc_w         #972                // String TetherMaxRoamPos
     176: aload_0
     177: getfield      #207                // Field maxRoamPos:Lnet/minecraft/class_2338;
     180: invokestatic  #1009               // Method net/minecraft/class_2512.method_10692:(Lnet/minecraft/class_2338;)Lnet/minecraft/class_2520;
     183: invokevirtual #1005               // Method net/minecraft/class_2487.method_10566:(Ljava/lang/String;Lnet/minecraft/class_2520;)Lnet/minecraft/class_2520;
     186: pop
     187: aload_0
     188: getfield      #214                // Field ownerId:Ljava/util/UUID;
     191: dup
     192: ifnull        212
     195: astore        6
     197: iconst_0
     198: istore        7
     200: aload_1
     201: ldc_w         #911                // String TetherOwnerId
     204: aload         6
     206: invokevirtual #990                // Method net/minecraft/class_2487.method_25927:(Ljava/lang/String;Ljava/util/UUID;)V
     209: goto          214
     212: pop
     213: nop
     214: aload_1
     215: ldc_w         #923                // String TetherOwnerName
     218: aload_0
     219: getfield      #179                // Field ownerName:Ljava/lang/String;
     222: invokevirtual #1013               // Method net/minecraft/class_2487.method_10582:(Ljava/lang/String;Ljava/lang/String;)V
     225: return

  private static final boolean canAddPokemon$lambda$1(com.cobblemon.mod.common.entity.pokemon.PokemonEntity);
    Code:
       0: iconst_1
       1: ireturn

  private static final boolean canAddPokemon$lambda$2(kotlin.jvm.functions.Function1, java.lang.Object);
    Code:
       0: aload_0
       1: aload_1
       2: invokeinterface #1017,  2         // InterfaceMethod kotlin/jvm/functions/Function1.invoke:(Ljava/lang/Object;)Ljava/lang/Object;
       7: checkcast     #649                // class java/lang/Boolean
      10: invokevirtual #1020               // Method java/lang/Boolean.booleanValue:()Z
      13: ireturn

  private static final kotlin.Unit tether$lambda$0(com.cobblemon.mod.common.entity.pokemon.PokemonEntity);
    Code:
       0: aload_0
       1: invokevirtual #1023               // Method com/cobblemon/mod/common/entity/pokemon/PokemonEntity.getPokemon:()Lcom/cobblemon/mod/common/pokemon/Pokemon;
       4: invokevirtual #1026               // Method com/cobblemon/mod/common/pokemon/Pokemon.getShiny:()Z
       7: ifeq          92
      10: new           #1028               // class com/cobblemon/mod/common/net/messages/client/effect/SpawnSnowstormEntityParticlePacket
      13: dup
      14: ldc_w         #1030               // String shiny_ring
      17: invokestatic  #1035               // Method com/cobblemon/mod/common/util/MiscUtilsKt.cobblemonResource:(Ljava/lang/String;)Lnet/minecraft/class_2960;
      20: aload_0
      21: invokevirtual #541                // Method com/cobblemon/mod/common/entity/pokemon/PokemonEntity.method_5628:()I
      24: iconst_2
      25: anewarray     #934                // class java/lang/String
      28: astore_1
      29: aload_1
      30: iconst_0
      31: ldc_w         #1037               // String shiny_particles
      34: aastore
      35: aload_1
      36: iconst_1
      37: ldc_w         #1039               // String middle
      40: aastore
      41: aload_1
      42: invokestatic  #1043               // Method kotlin/collections/CollectionsKt.listOf:([Ljava/lang/Object;)Ljava/util/List;
      45: aconst_null
      46: aconst_null
      47: bipush        24
      49: aconst_null
      50: invokespecial #1046               // Method com/cobblemon/mod/common/net/messages/client/effect/SpawnSnowstormEntityParticlePacket."<init>":(Lnet/minecraft/class_2960;ILjava/util/List;Ljava/lang/Integer;Ljava/util/List;ILkotlin/jvm/internal/DefaultConstructorMarker;)V
      53: checkcast     #352                // class com/cobblemon/mod/common/api/net/NetworkPacket
      56: aload_0
      57: invokevirtual #1049               // Method com/cobblemon/mod/common/entity/pokemon/PokemonEntity.method_23317:()D
      60: aload_0
      61: invokevirtual #1052               // Method com/cobblemon/mod/common/entity/pokemon/PokemonEntity.method_23318:()D
      64: aload_0
      65: invokevirtual #1055               // Method com/cobblemon/mod/common/entity/pokemon/PokemonEntity.method_23321:()D
      68: ldc2_w        #1056               // double 64.0d
      71: aload_0
      72: invokevirtual #1058               // Method com/cobblemon/mod/common/entity/pokemon/PokemonEntity.method_37908:()Lnet/minecraft/class_1937;
      75: invokevirtual #1062               // Method net/minecraft/class_1937.method_27983:()Lnet/minecraft/class_5321;
      78: dup
      79: ldc_w         #1064               // String dimension(...)
      82: invokestatic  #198                // Method kotlin/jvm/internal/Intrinsics.checkNotNullExpressionValue:(Ljava/lang/Object;Ljava/lang/String;)V
      85: aconst_null
      86: bipush        32
      88: aconst_null
      89: invokestatic  #1068               // InterfaceMethod com/cobblemon/mod/common/api/net/NetworkPacket.sendToPlayersAround$default:(Lcom/cobblemon/mod/common/api/net/NetworkPacket;DDDDLnet/minecraft/class_5321;Lkotlin/jvm/functions/Function1;ILjava/lang/Object;)V
      92: aload_0
      93: ldc_w         #1069               // float 1.5f
      96: aload_0
      97: invokedynamic #1074,  0           // InvokeDynamic #4:invoke:(Lcom/cobblemon/mod/common/entity/pokemon/PokemonEntity;)Lkotlin/jvm/functions/Function0;
     102: invokevirtual #1077               // Method com/cobblemon/mod/common/entity/pokemon/PokemonEntity.after:(FLkotlin/jvm/functions/Function0;)Lcom/cobblemon/mod/common/api/scheduling/ScheduledTask;
     105: pop
     106: getstatic     #1082               // Field kotlin/Unit.INSTANCE:Lkotlin/Unit;
     109: areturn

  private static final kotlin.Unit tether$lambda$0$0(com.cobblemon.mod.common.entity.pokemon.PokemonEntity);
    Code:
       0: aload_0
       1: iconst_0
       2: invokevirtual #486                // Method com/cobblemon/mod/common/entity/pokemon/PokemonEntity.setBeamMode:(I)V
       5: getstatic     #1082               // Field kotlin/Unit.INSTANCE:Lkotlin/Unit;
       8: areturn

  private static final boolean getInRangeViewerCount$lambda$0(kotlin.jvm.functions.Function1, java.lang.Object);
    Code:
       0: aload_0
       1: aload_1
       2: invokeinterface #1017,  2         // InterfaceMethod kotlin/jvm/functions/Function1.invoke:(Ljava/lang/Object;)Ljava/lang/Object;
       7: checkcast     #649                // class java/lang/Boolean
      10: invokevirtual #1020               // Method java/lang/Boolean.booleanValue:()Z
      13: ireturn

  private static final void TICKER$lambda$0(net.minecraft.class_1937, net.minecraft.class_2338, net.minecraft.class_2680, com.cobblemon.mod.common.block.entity.PokemonPastureBlockEntity);
    Code:
       0: aload_0
       1: getfield      #621                // Field net/minecraft/class_1937.field_9236:Z
       4: ifeq          8
       7: return
       8: aload_3
       9: getfield      #168                // Field ticksUntilCheck:I
      12: istore        4
      14: aload_3
      15: iload         4
      17: iconst_m1
      18: iadd
      19: putfield      #168                // Field ticksUntilCheck:I
      22: aload_3
      23: getfield      #168                // Field ticksUntilCheck:I
      26: ifgt          33
      29: aload_3
      30: invokevirtual #1086               // Method checkPokemon:()V
      33: aload_3
      34: getfield      #176                // Field tetheredPokemon:Ljava/util/List;
      37: checkcast     #221                // class java/lang/Iterable
      40: astore        5
      42: iconst_0
      43: istore        6
      45: aload         5
      47: astore        7
      49: new           #170                // class java/util/ArrayList
      52: dup
      53: invokespecial #172                // Method java/util/ArrayList."<init>":()V
      56: checkcast     #223                // class java/util/Collection
      59: astore        8
      61: iconst_0
      62: istore        9
      64: aload         7
      66: invokeinterface #231,  1          // InterfaceMethod java/lang/Iterable.iterator:()Ljava/util/Iterator;
      71: astore        10
      73: aload         10
      75: invokeinterface #236,  1          // InterfaceMethod java/util/Iterator.hasNext:()Z
      80: ifeq          131
      83: aload         10
      85: invokeinterface #240,  1          // InterfaceMethod java/util/Iterator.next:()Ljava/lang/Object;
      90: astore        11
      92: aload         11
      94: checkcast     #115                // class com/cobblemon/mod/common/block/entity/PokemonPastureBlockEntity$Tethering
      97: astore        12
      99: iconst_0
     100: istore        13
     102: aload         12
     104: invokevirtual #793                // Method com/cobblemon/mod/common/block/entity/PokemonPastureBlockEntity$Tethering.getPokemon:()Lcom/cobblemon/mod/common/pokemon/Pokemon;
     107: ifnull        114
     110: iconst_1
     111: goto          115
     114: iconst_0
     115: ifeq          73
     118: aload         8
     120: aload         11
     122: invokeinterface #828,  2          // InterfaceMethod java/util/Collection.add:(Ljava/lang/Object;)Z
     127: pop
     128: goto          73
     131: aload         8
     133: checkcast     #174                // class java/util/List
     136: nop
     137: astore        4
     139: aload         4
     141: invokeinterface #985,  1          // InterfaceMethod java/util/List.iterator:()Ljava/util/Iterator;
     146: astore        5
     148: aload         5
     150: invokeinterface #236,  1          // InterfaceMethod java/util/Iterator.hasNext:()Z
     155: ifeq          215
     158: aload         5
     160: invokeinterface #240,  1          // InterfaceMethod java/util/Iterator.next:()Ljava/lang/Object;
     165: checkcast     #115                // class com/cobblemon/mod/common/block/entity/PokemonPastureBlockEntity$Tethering
     168: astore        6
     170: aload         6
     172: invokevirtual #793                // Method com/cobblemon/mod/common/block/entity/PokemonPastureBlockEntity$Tethering.getPokemon:()Lcom/cobblemon/mod/common/pokemon/Pokemon;
     175: dup
     176: invokestatic  #467                // Method kotlin/jvm/internal/Intrinsics.checkNotNull:(Ljava/lang/Object;)V
     179: astore        7
     181: aload         7
     183: invokevirtual #1089               // Method com/cobblemon/mod/common/pokemon/Pokemon.getCurrentFullness:()I
     186: ifle          195
     189: aload         7
     191: iconst_1
     192: invokevirtual #1092               // Method com/cobblemon/mod/common/pokemon/Pokemon.tickMetabolism:(I)V
     195: aload         7
     197: invokevirtual #1096               // Method com/cobblemon/mod/common/pokemon/Pokemon.getInteractionCooldowns:()Ljava/util/Map;
     200: invokestatic  #1102               // Method kotlin/collections/MapsKt.any:(Ljava/util/Map;)Z
     203: ifeq          148
     206: aload         7
     208: iconst_1
     209: invokevirtual #1105               // Method com/cobblemon/mod/common/pokemon/Pokemon.tickInteractionCooldown:(I)V
     212: goto          148
     215: aload_3
     216: aload_3
     217: invokestatic  #467                // Method kotlin/jvm/internal/Intrinsics.checkNotNull:(Ljava/lang/Object;)V
     220: aload_3
     221: aload_0
     222: invokestatic  #467                // Method kotlin/jvm/internal/Intrinsics.checkNotNull:(Ljava/lang/Object;)V
     225: aload_0
     226: aload_3
     227: invokevirtual #270                // Method method_11016:()Lnet/minecraft/class_2338;
     230: dup
     231: ldc_w         #272                // String getBlockPos(...)
     234: invokestatic  #198                // Method kotlin/jvm/internal/Intrinsics.checkNotNullExpressionValue:(Ljava/lang/Object;Ljava/lang/String;)V
     237: dconst_0
     238: iconst_4
     239: aconst_null
     240: invokestatic  #1107               // Method getInRangeViewerCount$default:(Lcom/cobblemon/mod/common/block/entity/PokemonPastureBlockEntity;Lnet/minecraft/class_1937;Lnet/minecraft/class_2338;DILjava/lang/Object;)I
     243: ifle          250
     246: iconst_1
     247: goto          251
     250: iconst_0
     251: invokespecial #1109               // Method togglePastureOn:(Z)V
     254: return

  public static final net.minecraft.class_5558 access$getTICKER$cp();
    Code:
       0: getstatic     #1116               // Field TICKER:Lnet/minecraft/class_5558;
       3: areturn

  public static final boolean access$isPlayerViewing(com.cobblemon.mod.common.block.entity.PokemonPastureBlockEntity, net.minecraft.class_3222);
    Code:
       0: aload_0
       1: aload_1
       2: invokespecial #1121               // Method isPlayerViewing:(Lnet/minecraft/class_3222;)Z
       5: ireturn

  static {};
    Code:
       0: new           #113                // class com/cobblemon/mod/common/block/entity/PokemonPastureBlockEntity$Companion
       3: dup
       4: aconst_null
       5: invokespecial #1125               // Method com/cobblemon/mod/common/block/entity/PokemonPastureBlockEntity$Companion."<init>":(Lkotlin/jvm/internal/DefaultConstructorMarker;)V
       8: putstatic     #1127               // Field Companion:Lcom/cobblemon/mod/common/block/entity/PokemonPastureBlockEntity$Companion;
      11: invokedynamic #1136,  0           // InvokeDynamic #5:tick:()Lnet/minecraft/class_5558;
      16: putstatic     #1116               // Field TICKER:Lnet/minecraft/class_5558;
      19: return
}
